{"level":67,"params":{"hp":111111,"attack":459,"defense":428,"focus":422,"elemFactor":[1,1,1.2,0.5],"statusInflict":[1,1,0.7,0.7],"statusEffect":[0.3,0.5,0.5,0.7]},"credit":5555,"exp":222,"maxSp":8,"enduranceScale":10,"healDropRate":0,"boss":true,"bossOrder":0,"padding":{"x":2,"y":2},"material":"METAL","aiGroup":"runbot","aiLearnType":"REGULAR","itemDrops":[{"item":"638","prob":1,"min":1,"max":1}],"targetDetect":{"detectDistance":80,"loseDistance":320,"notifyNeighbourRadius":100,"onDistance":true},"hpBreaks":[{"hp":0.8,"healDrop":0.15},{"hp":0.4,"healDrop":0.3}],"size":{"x":24,"y":24,"z":32},"anims":"enemies.mine-runbot-tremor","defaultState":"OFF","walkConfigs":{"normal":{"idle":"idle","move":"move","run":"run","damage":"damage","jump":"jump","fall":"fall"},"weak":{"idle":"preDash","damage":"damage"},"off":{"idle":"off"}},"_wm":{"attributes":{"activeIf":{"_type":"VarCondition","_info":"If true, enemy enables when player is nearby."}}},"walkAnims":"normal","weight":100,"maxVel":180,"jumpingEnabled":true,"shadow":32,"damageFactor":0.7,"ballFactor":0.7,"hitStable":"MEDIUM","DOCTYPE":"ENEMY","trackers":{"weakRegen":{"target":3.5,"initRandom":0,"resetRandom":0,"noStateReset":false,"noAssist":false,"type":"TIME"},"auraRegen":{"target":20,"initRandom":0,"resetRandom":0,"noStateReset":false,"noAssist":false,"type":"TIME"},"dash":{"target":11,"initRandom":0,"resetRandom":0,"noStateReset":false,"noAssist":false,"type":"TIME"},"shockHits":{"target":3,"scaleDmgFactor":true,"scaleEnemyFactor":true,"scaleElement":false,"noStateReset":false,"type":"HIT"}},"states":{"OFF":{"walkAnims":"off","weight":-1,"hitIgnore":true,"aggression":"PEACEFUL","choices":[{"req":[{"negated":false,"type":"VAR_CONDITION","condition":{"actorAttrib":"activeIf"}}],"preSwitchState":"IDLE"},{"action":"OffIdle"}]},"IDLE":{"walkAnims":"off","enabledReactions":["HP_BREAK","KILL_HIT"],"aggression":"PEACEFUL","choices":[{"req":[{"type":"!VAR_CONDITION","condition":{"actorAttrib":"activeIf"}}],"preSwitchState":"OFF"},{"req":[{"negated":false,"type":"HAS_TARGET"}],"action":"Activate","preSwitchState":"DEFAULT"},{"action":"OffIdle"}]},"DEFAULT":{"enabledReactions":["KILL_HIT","HP_BREAK","BALL_DODGE","SHOCK_SHIELDBREAK"],"choices":[{"req":[{"negated":false,"type":"TRACKER_READY","name":"auraRegen"},{"sticking":false,"group":"pushAura","type":"!HAS_PROXY"}],"action":"restoreAura"},{"req":[{"negated":false,"type":"ENTERED_STATE"},{"sticking":false,"group":"pushAura","type":"!HAS_PROXY"}],"action":"restoreAura"},{"req":[{"type":"!HAS_TARGET"}],"postSwitchState":"IDLE"},{"req":[{"distance":200,"throwing":false,"type":"!TARGET_REACHABLE"}],"action":"AdjustRun"},{"action":"Jump","frequency":"RARE","ignoreStun":true},{"req":[{"negated":false,"type":"TRACKER_READY","name":"dash"}],"action":"DashAttack","frequency":"OFTEN","ignoreStun":true},{"req":[{"min":96,"max":800,"negated":false,"type":"TARGET_DISTANCE"},{"min":1,"max":1,"negated":false,"type":"HP_BREAK"}],"action":"RangedAttack","frequency":"NORMAL","ignoreStun":true},{"req":[{"min":96,"max":800,"negated":false,"type":"TARGET_DISTANCE"},{"min":2,"negated":false,"type":"HP_BREAK"}],"action":"RangedAttack","frequency":"OFTEN","ignoreStun":true},{"req":[{"distance":120,"throwing":false,"type":"!TARGET_REACHABLE"}],"action":"Adjust"},{"action":"BattleIdle"}]},"WEAK":{"walkAnims":"weak","damageFactor":1.1,"ballFactor":1,"faceToTarget":false,"enabledReactions":["KILL_HIT","HP_BREAK"],"choices":[{"req":[{"negated":false,"type":"ENTERED_STATE"}],"action":"weakStart"},{"req":[{"negated":false,"type":"TRACKER_READY","name":"weakRegen"}],"action":"weakEnd","preSwitchState":"DEFAULT","ignoreStun":true}]},"PASSIVE_INVIS":{"weight":-1,"hitIgnore":true,"aggression":"PEACEFUL","annotate":{"active":"NONE","passive":"IMMUNE","weapon":"ANY","element":"ANY","extra":[]},"choices":[]},"PASSIVE_OFF":{"walkAnims":"off","weight":-1,"hitIgnore":true,"aggression":"PEACEFUL","annotate":{"active":"NONE","passive":"IMMUNE","weapon":"ANY","element":"ANY","extra":[]},"choices":[]}},"proxies":{"wavePushAura":{"copyOwnerAnims":false,"breakType":"COMBATANT","action":[{"duration":-1,"align":"BOTTOM","rotateFace":0,"flipLeftFace":false,"wait":false,"waitSkip":0,"actionDetached":false,"fixPos":false,"type":"SHOW_EFFECT","effect":{"sheet":"specials.wave","name":"wavePushSmall"},"offset":{"x":0,"y":0,"z":12}},{"align":"BOTTOM","radius":40,"yScale":0,"zHeight":20,"centralAngle":1,"duration":0.5,"expandRadius":0,"alwaysFull":true,"clockwise":false,"flipLeftFace":0,"rectangular":false,"repeat":true,"uniformHitDir":false,"fixPos":false,"checkCollision":true,"type":"CIRCLE_ATTACK","attack":{"type":"NONE","visualType":"LIGHT","element":"WAVE","damageFactor":0.2,"reverse":false,"status":4,"guardable":null,"skillBonus":"RANGED_DMG","limiter":null},"offset":{"x":0,"y":0,"z":16}},{"strength":"NO_ESCAPE","pull":false,"radius":32,"fadeRadius":28,"minRadius":0,"zHeight":16,"duration":-1,"align":"CENTER","type":"PUSH_PULL_FORCE"},{"name":"start","type":"LABEL"},{"time":0.5,"type":"WAIT"},{"name":"start","type":"GOTO_LABEL"}],"invisible":false,"hp":0,"stickToSource":"OWNER","stickFaceAlign":false,"group":"pushAura","startAnim":"","size":{"x":0,"y":0,"z":0},"config":{},"type":"GENERIC"},"waveGun":{"size":{"x":16,"y":16,"z":8},"effects":"specials.wave","effectKeys":{"trail":"waveGun","wall":"waveGunXplode","air":"waveGunXplode"},"speed":1200,"maxBounce":0,"timer":1,"trail":true,"multiHit":true,"light":"XL","noLightGlow":false,"type":"BALL","animation":{"name":"default","gfxOffset":{"x":0,"y":-4},"sheet":{"src":"media\/entity\/effects\/lighter-particle.png","offX":144,"offY":0,"width":16,"height":16},"renderMode":"lighter","time":0.05,"repeat":true,"frames":[0]},"attack":{"type":"HEAVY","element":"WAVE","damageFactor":4,"reverse":false,"spFactor":0,"guardable":"","skillBonus":"RANGED_DMG","limiter":""},"timeBoni":null,"behaviors":[]},"homingBall":{"effects":"ball-wave","speed":200,"maxBounce":0,"timer":1.7,"trail":false,"multiHit":false,"noLightGlow":true,"attack":{"type":"LIGHT","element":"WAVE","damageFactor":0.35,"reverse":false,"guardable":"","skillBonus":"RANGED_DMG","limiter":""},"timeBoni":null,"behaviors":[{"steerDegree":0.35,"adjustTime":0.9,"type":"FOLLOW_TARGET"},{"speedFactor":0.5,"startWait":0,"fadeOut":0.15,"fadeOutVary":0,"pause":0.25,"pauseVary":0,"fadeIn":0.4,"type":"SLOW_DOWN"}],"animation":{"SUB":[{"name":"default","sheet":{"src":"media\/entity\/enemy\/jungle-projectiles.png","offX":96,"offY":0,"width":16,"height":16},"renderMode":"lighter","time":0.033,"repeat":true,"frames":[0,1,2,3]}]},"type":"BALL"},"waveDashStun":{"copyOwnerAnims":false,"breakType":"COMBATANT","action":[{"selectType":"TARGET","hitDir":"TOWARD","align":"BOTTOM","hitCount":11,"hitDelay":0.15,"type":"DIRECT_HIT","attack":{"type":"HEAVY","visualType":"LIGHT","element":"WAVE","damageFactor":0.5,"reverse":false,"spFactor":0,"stunSteps":[{"type":"START_LOCK"},{"type":"BLOCK_XY"}],"status":1.25,"guardable":null,"skillBonus":"MELEE_DMG","limiter":null}},{"time":1.6,"type":"WAIT"}],"invisible":false,"hp":0,"stickToSource":"NONE","stickFaceAlign":false,"group":"","startAnim":"","size":{"x":0,"y":0,"z":0},"config":{"zGravityFactor":0},"type":"GENERIC"},"waveWall":{"copyOwnerAnims":false,"breakType":"COMBATANT","action":[{"duration":-1,"align":"CENTER","rotateFace":8,"flipLeftFace":false,"wait":false,"waitSkip":0,"actionDetached":false,"fixPos":false,"type":"SHOW_EFFECT","effect":{"sheet":"specials.wave","name":"waveDashRippleSlow"},"offset":{"x":0,"y":0,"z":0}},{"align":"BOTTOM","radius":40,"yScale":0,"zHeight":32,"centralAngle":1,"duration":0.3,"expandRadius":0,"alwaysFull":true,"clockwise":false,"flipLeftFace":0,"rectangular":false,"repeat":true,"uniformHitDir":false,"fixPos":false,"checkCollision":true,"type":"CIRCLE_ATTACK","attack":{"type":"NONE","visualType":"LIGHT","element":"WAVE","damageFactor":0.3,"reverse":false,"spFactor":0,"status":5,"guardable":null,"skillBonus":"RANGED_DMG","limiter":null},"offset":{"x":0,"y":0,"z":0}},{"time":1.2,"type":"WAIT"},{"type":"CLEAR_EFFECTS"}],"invisible":false,"hp":0,"stickToSource":"NONE","stickFaceAlign":false,"group":"wall","startAnim":"","type":"GENERIC","size":{"x":24,"y":24,"z":32},"config":{"collType":"NONE"}},"waveBulletSmall":{"size":{"x":16,"y":16,"z":16},"effects":"enemies.jungle","effectKeys":{"trail":"whaleBulletTrail"},"speed":150,"maxBounce":0,"timer":6,"trail":true,"multiHit":false,"light":"L","noLightGlow":true,"attack":{"type":"MEDIUM","element":"WAVE","damageFactor":0.5,"reverse":false,"guardable":"","skillBonus":"RANGED_DMG","limiter":""},"timeBoni":null,"behaviors":[],"animation":{"SUB":[{"name":"default","offset":{"x":0,"y":64,"z":64},"sheet":{"src":"media\/entity\/effects\/wave.png","xCount":6,"offX":0,"offY":128,"width":48,"height":48},"renderMode":"lighter","time":0.033,"repeat":true,"frames":[0,1,2,3,4,5,6,7,8,9,10]}]},"type":"BALL"},"laser":{"copyOwnerAnims":false,"breakType":"ACTION","action":[{"value":1,"forwardToProxies":false,"type":"SET_DAMAGE_CEILING"},{"duration":-1,"align":"BOTTOM","rotateFace":0,"flipLeftFace":false,"wait":false,"waitSkip":0,"actionDetached":false,"target2":"PROXY_OWNER","target2Align":"FACE","fixPos":false,"type":"SHOW_EFFECT","effect":{"sheet":"enemies.heat-dng","name":"darthMothLaser"},"offset":{"x":0,"y":0,"z":0}},{"align":"BOTTOM","radius":24,"yScale":0,"zHeight":0,"centralAngle":0,"duration":0.1,"expandRadius":0,"alwaysFull":true,"clockwise":false,"flipLeftFace":0,"rectangular":false,"repeat":true,"uniformHitDir":false,"fixPos":false,"checkCollision":false,"type":"CIRCLE_ATTACK","attack":{"type":"MEDIUM","element":"HEAT","damageFactor":0.8,"reverse":false,"status":7,"guardable":"","skillBonus":"RANGED_DMG","limiter":""},"offset":{"x":0,"y":0,"z":0}},{"value":500,"type":"SET_SPEED"},{"value":false,"type":"FACE_TO_TARGET"},{"time":0.1,"stopBeforeEdge":false,"type":"MOVE_FORWARD"},{"value":true,"type":"FACE_TO_TARGET"},{"time":0.05,"stopBeforeEdge":false,"type":"MOVE_FORWARD"},{"value":0.3,"type":"FACE_TO_TARGET_SPEED"},{"time":0.3,"stopBeforeEdge":false,"type":"MOVE_FORWARD"},{"value":0.5,"type":"FACE_TO_TARGET_SPEED"},{"value":450,"type":"SET_SPEED"},{"time":0.2,"stopBeforeEdge":false,"type":"MOVE_FORWARD"},{"value":0.6,"type":"FACE_TO_TARGET_SPEED"},{"value":400,"type":"SET_SPEED"},{"time":0.2,"stopBeforeEdge":false,"type":"MOVE_FORWARD"},{"value":0.7,"type":"FACE_TO_TARGET_SPEED"},{"value":350,"type":"SET_SPEED"},{"time":0.15,"stopBeforeEdge":false,"type":"MOVE_FORWARD"},{"value":300,"type":"SET_SPEED"},{"maxTime":0.1,"forceTime":true,"distance":0,"planOnly":false,"targetType":"ENEMY","precise":false,"type":"NAVIGATE_TO_TARGET"},{"value":250,"type":"SET_SPEED"},{"maxTime":0.1,"forceTime":true,"distance":0,"planOnly":false,"targetType":"ENEMY","precise":false,"type":"NAVIGATE_TO_TARGET"},{"withElse":false,"type":"IF","condition":false,"thenStep":[{"time":0.8,"stopBeforeEdge":false,"type":"MOVE_FORWARD"}]},{"type":"CLEAR_EFFECTS"}],"invisible":false,"hp":0,"stickToSource":"NONE","stickFaceAlign":false,"group":"","startAnim":"","size":{"x":24,"y":24,"z":0},"config":{},"type":"GENERIC"},"iceProjectilesSmall":{"effects":"ball","speed":450,"maxBounce":1,"timer":1.8,"trail":false,"multiHit":false,"noLightGlow":false,"type":"BALL","animation":{"name":"default","sheet":{"src":"media\/entity\/effects\/icicles.png","offX":144,"offY":16,"width":16,"height":24},"time":0.05,"repeat":true,"frames":[0]},"attack":{"type":"MEDIUM","element":"COLD","damageFactor":0.45,"reverse":false,"status":4,"guardable":"","skillBonus":"RANGED_DMG","limiter":""},"timeBoni":null,"behaviors":[{"speedFactor":0.05,"startWait":0,"fadeOut":0.15,"fadeOutVary":0,"pause":0.1,"pauseVary":0.1,"fadeIn":0.3,"type":"SLOW_DOWN"},{"steerDegree":0.15,"adjustTime":1,"type":"FOLLOW_TARGET"}]}},"actions":{"Activate":[{"type":"DISABLE_REACTION","reaction":"BALL_DODGE"},{"text":{"en_US":"Threat detected","pt_BR":"Ameaça Detectada","de_DE":"Bedrohung entdeckt<<C<<Gepr\u00fcft: Minsu","fr_FR":"fr_FR","langUid":38,"zh_CN":"\u68c0\u6d4b\u5230\u5a01\u80c1<<A<<[CHANGED 2021\/02\/19]","ko_KR":"\uc704\ud611 \uac10\uc9c0<<A<<[CHANGED 2021\/02\/16]","ja_JP":"\u8105\u5a01\u3092\u5bdf\u77e5<<A<<[CHANGED 2021\/02\/09]","zh_TW":"\u6aa2\u6e2c\u5230\u5a01\u8105<<A<<[CHANGED 2021\/02\/19]"},"mode":"NO_LINE","color":"RED","actionDetached":true,"hideOutsideOfScreen":false,"time":1,"type":"SHOW_AR_MSG"},{"wait":true,"viaWalkConfig":false,"anim":"boot","type":"SHOW_ANIMATION"},{"time":0.2,"type":"WAIT"},{"value":true,"type":"FACE_TO_TARGET"},{"name":"shield","actionDetached":true,"type":"ADD_SHIELD","shield":{"type":"DIRECTIONAL","settings":{"baseFactor":0.5,"strength":"BLOCK_ALL","stableOverride":"MASSIVE","duration":-1,"range":1,"back":false}}},{"align":"BOTTOM","type":"SHOOT_PROXY","proxy":"wavePushAura","offset":{"x":0,"y":0,"z":0}},{"target":"PROXY_OWNER","align":"BOTTOM","duration":0,"type":"STICK_TO_TARGET","offset":{"x":0,"y":0,"z":0}},{"time":0.5,"type":"WAIT"}],"OffIdle":[{"minTime":0.1,"maxTime":0.3,"type":"WAIT_RANDOM"}],"Idle":[{"value":true,"type":"FACE_TO_TARGET"},{"minTime":0.1,"maxTime":0.3,"type":"WAIT_RANDOM"}],"BattleIdle":[{"value":true,"type":"FACE_TO_TARGET"},{"minTime":0.2,"maxTime":0.4,"type":"WAIT_RANDOM"}],"MoveToSpawnPoint":[{"value":0.5,"type":"SET_RELATIVE_SPEED"},{"maxTime":3,"maxDistance":16,"precise":false,"type":"NAVIGATE_TO_SPAWN_POINT"}],"MoveRandom":[{"value":0.3,"type":"SET_RELATIVE_SPEED"},{"value":false,"type":"SET_JUMPING"},{"minTime":0.3,"maxTime":0.5,"dirChanges":0,"stopBeforeEdge":true,"type":"MOVE_RANDOM"},{"minTime":0.5,"maxTime":0.6,"type":"WAIT_RANDOM"}],"AdjustRun":[{"value":1.3,"type":"SET_RELATIVE_SPEED"},{"duration":-1,"align":"BOTTOM","rotateFace":0,"flipLeftFace":false,"wait":false,"waitSkip":0,"actionDetached":false,"fixPos":false,"type":"SHOW_EFFECT","effect":{"sheet":"dust","name":"line"}},{"maxTime":1,"forceTime":false,"distance":100,"planOnly":false,"targetType":"ENEMY","precise":false,"stayBehind":false,"type":"NAVIGATE_TO_TARGET"}],"Adjust":[{"value":0.6,"type":"SET_RELATIVE_SPEED"},{"maxTime":1,"forceTime":false,"distance":100,"planOnly":false,"targetType":"ENEMY","precise":false,"stayBehind":false,"type":"NAVIGATE_TO_TARGET"}],"GetClose":[{"value":0.7,"type":"SET_RELATIVE_SPEED"},{"value":"MEDIUM","type":"SET_HIT_STABLE"},{"maxTime":0.5,"forceTime":false,"distance":60,"planOnly":false,"targetType":"ENEMY","precise":false,"stayBehind":false,"type":"NAVIGATE_TO_TARGET"}],"DashAttack":[{"value":0.7,"type":"SET_RELATIVE_SPEED"},{"value":"HEAVY","type":"SET_HIT_STABLE"},{"maxTime":0.5,"forceTime":false,"distance":70,"planOnly":false,"targetType":"ENEMY","precise":false,"stayBehind":false,"type":"NAVIGATE_TO_TARGET"},{"type":"DISABLE_REACTION","reaction":"BALL_DODGE"},{"active":"PRE_ATTACK","passive":"VULNERABLE","type":"CHANGE_ENEMY_ANNOTATION"},{"value":1,"type":"SET_RELATIVE_SPEED"},{"value":true,"type":"FACE_TO_TARGET"},{"value":"MASSIVE","type":"SET_HIT_STABLE"},{"duration":-1,"align":"BOTTOM","rotateFace":0,"flipLeftFace":false,"wait":false,"waitSkip":0,"actionDetached":false,"fixPos":false,"type":"SHOW_EFFECT","effect":{"sheet":"enemies.mine-bots","name":"preDash"},"offset":{"x":0,"y":0,"z":0}},{"wait":false,"viaWalkConfig":false,"type":"SHOW_ANIMATION","anim":"preDash"},{"aggroTime":0.8,"time":1,"type":"WAIT"},{"type":"CLEAR_EFFECTS"},{"type":"CLEAR_ANIMATION"},{"conditions":[{"min":2,"negated":false,"type":"HP_BREAK"}],"withElse":false,"type":"COMBAT_IF","thenStep":[{"volume":0.5,"variance":0.1,"global":false,"loop":false,"speed":1.5,"type":"PLAY_SOUND","sound":"media\/sound\/boss\/turret\/big-shot.ogg"},{"volume":0.6,"variance":0.1,"global":false,"loop":false,"speed":2,"type":"PLAY_SOUND","sound":"media\/sound\/battle\/wave-hit.ogg"},{"changeType":"set","type":"SET_ATTRIB_NUMBER","attribName":"temp","value":{"varName":"entity.hpBreak"}},{"withElse":false,"type":"IF","condition":"newgame.harder-enemies","thenStep":[{"changeType":"add","type":"SET_ATTRIB_NUMBER","attribName":"temp","value":1}]},{"changeType":"mul","type":"SET_ATTRIB_NUMBER","attribName":"temp","value":2},{"align":"BOTTOM","centralAngle":0.6,"startAngle":0.4,"angleVary":0,"startDistCollide":"NONE","random":false,"clockwise":false,"flipLeftFace":0,"circularArea":false,"uniformDir":0,"delay":0,"repeat":false,"duration":0.04,"type":"SHOOT_PROXY_RANGE","proxy":"homingBall","offset":{"x":0,"y":0,"z":0},"count":{"varName":"entity.attrib.temp"}}]},{"value":2.5,"type":"SET_RELATIVE_SPEED"},{"duration":-1,"align":"CENTER","rotateFace":8,"flipLeftFace":false,"wait":false,"waitSkip":0,"actionDetached":false,"group":"dash","fixPos":false,"type":"SHOW_EFFECT","effect":{"sheet":"specials.wave","name":"waveDashTrail"},"offset":{"x":0,"y":0,"z":0}},{"value":0.4,"type":"SET_INVINCIBLE"},{"align":"BOTTOM","centralAngle":0,"angleVary":0,"startDistCollide":"NONE","random":false,"clockwise":false,"flipLeftFace":0,"circularArea":false,"uniformDir":0,"delay":0.016,"repeat":true,"duration":0.12,"count":1,"type":"SHOOT_PROXY_RANGE","proxy":"waveWall","offset":{"x":0,"y":0,"z":0}},{"duration":-1,"align":"BOTTOM","rotateFace":0,"flipLeftFace":false,"wait":false,"waitSkip":0,"actionDetached":false,"fixPos":false,"type":"SHOW_EFFECT","effect":{"sheet":"dust","name":"line"}},{"volume":0.8,"global":false,"loop":false,"type":"PLAY_SOUND","sound":"media\/sound\/battle\/dash-2.ogg"},{"value":"IGNORE","type":"SET_COLL_TYPE"},{"value":false,"type":"FACE_TO_TARGET"},{"type":"ENABLE_REACTION","reaction":"DASH_WALL_HIT"},{"active":"ATTACK","type":"CHANGE_ENEMY_ANNOTATION"},{"value":2,"forwardToProxies":false,"type":"SET_DAMAGE_CEILING"},{"time":0.8,"missReactTime":0.05,"cancelOnHit":true,"withBranches":true,"orthoDirFactor":0,"ignoreLastHit":false,"collideSlip":false,"type":"TACKLE","attack":{"type":"MASSIVE","element":"NEUTRAL","damageFactor":1.2,"fly":"MASSIVE+","reverse":false,"guardable":"","skillBonus":"","limiter":""},"hit":[{"type":"STOP_REPEATING_FORCE"},{"group":"line","type":"CLEAR_EFFECTS"},{"wait":false,"viaWalkConfig":false,"type":"SHOW_ANIMATION","anim":"brake"},{"value":0.3,"type":"SET_FRICTION"},{"forceValue":0.4,"type":"RESET_TRACKER","tracker":"dash"},{"time":0.5,"type":"WAIT"}],"missed":[{"value":0.2,"type":"SET_RELATIVE_SPEED"},{"group":"line","type":"CLEAR_EFFECTS"},{"value":0.3,"type":"SET_FRICTION"},{"wait":false,"viaWalkConfig":false,"type":"SHOW_ANIMATION","anim":"brake"},{"time":0.1,"stopBeforeEdge":false,"type":"MOVE_FORWARD"},{"time":0.3,"type":"WAIT"},{"type":"STOP_REPEATING_FORCE"},{"type":"DISABLE_REACTION","reaction":"DASH_WALL_HIT"},{"type":"SET_RELATIVE_SPEED","value":0.2},{"type":"ENABLE_REACTION","reaction":"WEAK_SPOT"},{"duration":-1,"align":"BOTTOM","rotateFace":0,"flipLeftFace":false,"wait":false,"waitSkip":0,"actionDetached":false,"group":"weak","fixPos":false,"type":"SHOW_EFFECT","effect":{"sheet":"charge","name":"light"},"offset":{"x":0,"y":0,"z":0}},{"conditions":[{"min":1,"negated":false,"type":"HP_BREAK"}],"withElse":true,"type":"COMBAT_IF","thenStep":[{"name":"slide","type":"LABEL"},{"changeType":"set","type":"SET_ATTRIB_NUMBER","attribName":"velX","value":{"varName":"entity.vel.x"}},{"withElse":false,"type":"IF","condition":"entity.attrib.velX < 0","thenStep":[{"changeType":"mul","type":"SET_ATTRIB_NUMBER","attribName":"velX","value":-1}]},{"changeType":"set","type":"SET_ATTRIB_NUMBER","attribName":"velY","value":{"varName":"entity.vel.y"}},{"withElse":false,"type":"IF","condition":"entity.attrib.velY < 0","thenStep":[{"changeType":"mul","type":"SET_ATTRIB_NUMBER","attribName":"velY","value":-1}]},{"withElse":true,"type":"IF","condition":"entity.attrib.velX < entity.attrib.velY","thenStep":[{"changeType":"div","type":"SET_ATTRIB_NUMBER","attribName":"velX","value":2}],"elseStep":[{"changeType":"div","type":"SET_ATTRIB_NUMBER","attribName":"velY","value":2}]},{"changeType":"set","type":"SET_ATTRIB_NUMBER","attribName":"vel","value":{"varName":"entity.attrib.velX"}},{"changeType":"add","type":"SET_ATTRIB_NUMBER","attribName":"vel","value":{"varName":"entity.attrib.velY"}},{"type":"WAIT","time":0.05},{"withElse":false,"type":"IF","condition":"entity.attrib.vel > 10","thenStep":[{"name":"slide","type":"GOTO_LABEL"}]},{"group":"dash","type":"CLEAR_EFFECTS"},{"type":"DISABLE_REACTION","reaction":"WEAK_SPOT"},{"group":"weak","type":"CLEAR_EFFECTS"},{"value":true,"type":"FACE_TO_TARGET"},{"time":0.1,"type":"WAIT"},{"value":1,"type":"SET_FRICTION"},{"value":0.2,"type":"SET_RELATIVE_SPEED"},{"type":"CLEAR_ANIMATION"},{"time":0.2,"stopBeforeEdge":false,"type":"MOVE_FORWARD"},{"value":1.2,"forwardToProxies":false,"type":"SET_DAMAGE_CEILING"},{"conditions":[{"min":2,"negated":false,"type":"HP_BREAK"}],"withElse":false,"type":"COMBAT_IF","thenStep":[{"value":1.5,"forwardToProxies":false,"type":"SET_DAMAGE_CEILING"}]},{"type":"SELECT_RANDOM","options":[{"0":" ","count":1,"weight":1},{"0":" ","count":1,"weight":1}],"0_0":[{"type":"ENABLE_REACTION","reaction":"WEAK_SPOT_COLD"},{"duration":-1,"align":"FACE","rotateFace":0,"flipLeftFace":false,"wait":false,"waitSkip":0,"actionDetached":false,"group":"charge","fixPos":false,"type":"SHOW_EFFECT","effect":{"sheet":"enemies.heat-dng","name":"mothBigCharge"},"offset":{"x":0,"y":0,"z":0}},{"time":1.1,"stopBeforeEdge":false,"type":"MOVE_FORWARD"},{"group":"charge","type":"CLEAR_EFFECTS"},{"wait":false,"viaWalkConfig":false,"type":"SHOW_ANIMATION","anim":"brake"},{"duration":-1,"align":"FACE","rotateFace":0,"flipLeftFace":false,"wait":false,"waitSkip":0,"actionDetached":false,"group":"shot","fixPos":false,"type":"SHOW_EFFECT","effect":{"sheet":"enemies.heat-dng","name":"darthMothLaserSrc"},"offset":{"x":0,"y":0,"z":0}},{"time":0.1,"type":"WAIT"},{"active":"ATTACK","type":"CHANGE_ENEMY_ANNOTATION"},{"value":false,"immediately":true,"type":"FACE_TO_TARGET"},{"align":"BOTTOM","centralAngle":0.1,"angleVary":0,"startDistCollide":"NONE","random":false,"clockwise":false,"flipLeftFace":0,"circularArea":false,"uniformDir":0,"delay":0,"repeat":false,"duration":0,"type":"SHOOT_PROXY_RANGE","proxy":"laser","offset":{"x":0,"y":0,"z":0},"count":{"varName":"entity.hpBreak"}}],"1_0":[{"type":"ENABLE_REACTION","reaction":"WEAK_SPOT_HEAT"},{"duration":-1,"align":"FACE","rotateFace":0,"flipLeftFace":false,"wait":false,"waitSkip":0,"actionDetached":false,"group":"charge","fixPos":false,"type":"SHOW_EFFECT","effect":{"sheet":"specials.cold","name":"coldMegaCharge"},"offset":{"x":0,"y":0,"z":0}},{"time":0.7,"stopBeforeEdge":false,"type":"MOVE_FORWARD"},{"group":"charge","type":"CLEAR_EFFECTS"},{"wait":false,"viaWalkConfig":false,"type":"SHOW_ANIMATION","anim":"brake"},{"duration":0.1,"align":"FACE","rotateFace":0,"flipLeftFace":false,"wait":false,"waitSkip":0,"actionDetached":false,"group":"shot","fixPos":false,"type":"SHOW_EFFECT","effect":{"sheet":"specials.cold","name":"coldQuickShoot"},"offset":{"x":0,"y":0,"z":0}},{"time":0.1,"type":"WAIT"},{"active":"ATTACK","type":"CHANGE_ENEMY_ANNOTATION"},{"value":false,"immediately":true,"type":"FACE_TO_TARGET"},{"changeType":"set","type":"SET_ATTRIB_NUMBER","attribName":"temp","value":{"varName":"entity.hpBreak"}},{"changeType":"mul","type":"SET_ATTRIB_NUMBER","attribName":"temp","value":2},{"changeType":"add","type":"SET_ATTRIB_NUMBER","attribName":"temp","value":1},{"align":"BOTTOM","centralAngle":0.1,"angleVary":0,"startDistCollide":"NONE","random":false,"clockwise":false,"flipLeftFace":0,"circularArea":false,"uniformDir":0,"delay":0,"repeat":false,"duration":0,"type":"SHOOT_PROXY_RANGE","proxy":"iceProjectilesSmall","offset":{"x":0,"y":0,"z":0},"count":{"varName":"entity.attrib.temp"}},{"type":"DISABLE_REACTION","reaction":"WEAK_SPOT_HEAT"}]},{"active":"POST_ATTACK","passive":"VULNERABLE","type":"CHANGE_ENEMY_ANNOTATION"},{"group":"shot","type":"CLEAR_EFFECTS"},{"type":"SET_RELATIVE_SPEED","value":1.5},{"time":0.2,"stopBeforeEdge":false,"type":"MOVE_BACKWARD"},{"value":0.3,"type":"SET_FRICTION"},{"type":"DISABLE_REACTION","reaction":"WEAK_SPOT_COLD"},{"type":"ENABLE_REACTION","reaction":"WEAK_SPOT"},{"duration":-1,"align":"BOTTOM","rotateFace":0,"flipLeftFace":false,"wait":false,"waitSkip":0,"actionDetached":false,"group":"weak","fixPos":false,"type":"SHOW_EFFECT","effect":{"sheet":"charge","name":"light"},"offset":{"x":0,"y":0,"z":0}}],"elseStep":[{"group":"dash","type":"CLEAR_EFFECTS"},{"type":"ENABLE_REACTION","reaction":"WEAK_SPOT"},{"duration":-1,"align":"BOTTOM","rotateFace":0,"flipLeftFace":false,"wait":false,"waitSkip":0,"actionDetached":false,"group":"weak","fixPos":false,"type":"SHOW_EFFECT","effect":{"sheet":"charge","name":"light"},"offset":{"x":0,"y":0,"z":0}},{"time":0.5,"type":"WAIT"}]},{"aggroTime":1.7,"time":2,"type":"WAIT"}]}],"DashWallHit":[{"value":"MASSIVE","type":"SET_HIT_STABLE"},{"type":"DISABLE_REACTION","reaction":"BALL_DODGE"},{"forceValue":0.4,"type":"RESET_TRACKER","tracker":"dash"},{"changeType":"set","type":"SET_ATTRIB_NUMBER","attribName":"temp","value":{"varName":"entity.hpBreak"}},{"changeType":"add","type":"SET_ATTRIB_NUMBER","attribName":"temp","value":2},{"withElse":false,"type":"IF","condition":"newgame.harder-enemies","thenStep":[{"changeType":"add","type":"SET_ATTRIB_NUMBER","attribName":"temp","value":2}]},{"align":"BOTTOM","centralAngle":0.3,"startAngle":0.2,"angleVary":0.05,"startDist":16,"startDistCollide":"NONE","random":true,"clockwise":false,"flipLeftFace":0,"circularArea":false,"uniformDir":0,"delay":0,"repeat":false,"duration":0.1,"count":{"varName":"entity.attrib.temp"},"type":"SHOOT_PROXY_RANGE","proxy":"waveBulletSmall","offset":{"x":0,"y":0,"z":0}},{"changeType":"mul","type":"SET_ATTRIB_NUMBER","attribName":"temp","value":2},{"align":"BOTTOM","centralAngle":0.3,"startAngle":0.6,"angleVary":0.05,"startDist":16,"startDistCollide":"NONE","random":true,"clockwise":false,"flipLeftFace":0,"circularArea":false,"uniformDir":0,"delay":0,"repeat":false,"duration":0.1,"count":{"varName":"entity.attrib.temp"},"type":"SHOOT_PROXY_RANGE","proxy":"waveBulletSmall","offset":{"x":0,"y":0,"z":0}},{"duration":0,"align":"BOTTOM","rotateFace":0,"flipLeftFace":false,"wait":false,"waitSkip":0,"actionDetached":false,"fixPos":false,"type":"SHOW_EFFECT","effect":{"sheet":"combat","name":"flashShort"}},{"volume":0.9,"global":false,"loop":false,"type":"PLAY_SOUND","sound":"media\/sound\/battle\/thud-4.ogg"},{"rumbleType":"RANDOM","name":"","duration":0.4,"power":"STRONGER","speed":"FASTER","fade":false,"type":"RUMBLE_SCREEN"},{"wait":false,"viaWalkConfig":false,"type":"SHOW_ANIMATION","anim":"brake"},{"value":0.5,"type":"SET_Z_BOUNCINESS"},{"value":200,"type":"SET_Z_VEL"},{"value":1.5,"type":"SET_RELATIVE_SPEED"},{"time":0.2,"stopBeforeEdge":false,"type":"MOVE_BACKWARD"},{"aggroTime":0.5,"time":0.7,"type":"WAIT"}],"DashStagger":[{"active":"POST_ATTACK","passive":"VULNERABLE","type":"CHANGE_ENEMY_ANNOTATION"},{"wait":false,"viaWalkConfig":false,"type":"SHOW_ANIMATION","anim":"brake"},{"type":"ENABLE_REACTION","reaction":"WEAK_SPOT"},{"duration":-1,"align":"BOTTOM","rotateFace":0,"flipLeftFace":false,"wait":false,"waitSkip":0,"actionDetached":false,"group":"weak","fixPos":false,"type":"SHOW_EFFECT","effect":{"sheet":"charge","name":"light"},"offset":{"x":0,"y":0,"z":0}},{"type":"SET_RELATIVE_SPEED","value":1.5},{"time":0.1,"stopBeforeEdge":false,"type":"MOVE_BACKWARD"},{"value":0.2,"type":"SET_FRICTION"},{"aggroTime":2.1,"time":2.5,"type":"WAIT"}],"Jump":[{"value":1.5,"type":"SET_RELATIVE_SPEED"},{"value":"MASSIVE","type":"SET_HIT_STABLE"},{"value":true,"type":"FACE_TO_TARGET"},{"active":"PRE_ATTACK","type":"CHANGE_ENEMY_ANNOTATION"},{"type":"DISABLE_REACTION","reaction":"BALL_DODGE"},{"duration":-1,"align":"BOTTOM","rotateFace":0,"flipLeftFace":false,"wait":false,"waitSkip":0,"actionDetached":false,"group":"charge","fixPos":false,"type":"SHOW_EFFECT","effect":{"sheet":"enemies.glitch-boss","name":"frobbitCharge"},"offset":{"x":0,"y":0,"z":0}},{"jumpHeight":"L","wait":true,"ignoreSounds":false,"type":"JUMP"},{"jumpHeight":"L","wait":true,"ignoreSounds":false,"type":"JUMP"},{"jumpHeight":"L","wait":true,"ignoreSounds":false,"type":"JUMP"},{"group":"charge","type":"CLEAR_EFFECTS"},{"duration":-1,"align":"CENTER","rotateFace":0,"flipLeftFace":false,"wait":false,"waitSkip":0,"actionDetached":false,"group":"line","fixPos":false,"type":"SHOW_EFFECT","effect":{"sheet":"enemies.glitch-boss","name":"frobbitAura"},"offset":{"x":0,"y":0,"z":0}},{"maxTime":0.5,"forceTime":false,"distance":80,"planOnly":false,"targetType":"ENEMY","precise":false,"stayBehind":false,"type":"NAVIGATE_TO_TARGET"},{"type":"CLEAR_EFFECTS"},{"value":"MASSIVE","type":"SET_HIT_STABLE"},{"value":1.2,"type":"SET_RELATIVE_SPEED"},{"duration":0,"align":"BOTTOM","rotateFace":0,"flipLeftFace":false,"wait":false,"waitSkip":0,"actionDetached":false,"fixPos":false,"type":"SHOW_EFFECT","effect":{"sheet":"dust","name":"backMedium"}},{"value":"IGNORE","type":"SET_COLL_TYPE"},{"active":"ATTACK","type":"CHANGE_ENEMY_ANNOTATION"},{"jumpSpeed":250,"adjustAbove":12,"type":"JUMP_TO_TARGET"},{"value":2,"forwardToProxies":false,"type":"SET_DAMAGE_CEILING"},{"conditions":[{"min":1,"negated":false,"type":"HP_BREAK"}],"withElse":false,"type":"COMBAT_IF","thenStep":[{"value":2.5,"forwardToProxies":false,"type":"SET_DAMAGE_CEILING"},{"conditions":[{"min":2,"negated":false,"type":"HP_BREAK"}],"withElse":false,"type":"COMBAT_IF","thenStep":[{"value":3,"forwardToProxies":false,"type":"SET_DAMAGE_CEILING"}]}]},{"align":"BOTTOM","radius":24,"yScale":0,"zHeight":64,"centralAngle":0,"duration":0,"expandRadius":0,"alwaysFull":false,"clockwise":false,"flipLeftFace":0,"rectangular":false,"repeat":false,"uniformHitDir":false,"fixPos":false,"checkCollision":false,"type":"CIRCLE_ATTACK","attack":{"type":"MASSIVE","element":"NEUTRAL","damageFactor":0.8,"fly":"MASSIVE+","reverse":false,"spFactor":0,"guardable":"","skillBonus":"","limiter":""},"offset":{"x":0,"y":0,"z":0}},{"align":"BOTTOM","radius":56,"yScale":0,"zHeight":64,"centralAngle":0,"duration":0,"expandRadius":0,"alwaysFull":false,"clockwise":false,"flipLeftFace":0,"rectangular":false,"repeat":false,"uniformHitDir":false,"fixPos":false,"checkCollision":false,"type":"CIRCLE_ATTACK","attack":{"type":"MASSIVE","element":"WAVE","damageFactor":1,"reverse":false,"spFactor":0,"status":5,"guardable":"","skillBonus":"","limiter":""},"offset":{"x":0,"y":0,"z":0}},{"conditions":[{"min":1,"negated":false,"type":"HP_BREAK"}],"withElse":false,"type":"COMBAT_IF","thenStep":[{"volume":0.5,"variance":0.1,"global":false,"loop":false,"speed":1.5,"type":"PLAY_SOUND","sound":"media\/sound\/boss\/turret\/big-shot.ogg"},{"volume":0.6,"variance":0.1,"global":false,"loop":false,"speed":2,"type":"PLAY_SOUND","sound":"media\/sound\/battle\/wave-hit.ogg"},{"changeType":"set","type":"SET_ATTRIB_NUMBER","attribName":"temp","value":{"varName":"entity.hpBreak"}},{"changeType":"mul","type":"SET_ATTRIB_NUMBER","attribName":"temp","value":2},{"align":"BOTTOM","centralAngle":0.8,"angleVary":0,"startDistCollide":"NONE","random":false,"clockwise":false,"flipLeftFace":0,"circularArea":false,"uniformDir":0,"delay":0,"repeat":false,"duration":0.04,"type":"SHOOT_PROXY_RANGE","proxy":"homingBall","offset":{"x":0,"y":0,"z":0},"count":{"varName":"entity.attrib.temp"}}]},{"volume":1,"global":false,"loop":false,"type":"PLAY_SOUND","sound":"media\/sound\/battle\/thud-5.ogg"},{"duration":0,"align":"BOTTOM","rotateFace":0,"flipLeftFace":false,"wait":false,"waitSkip":0,"actionDetached":false,"fixPos":false,"type":"SHOW_EFFECT","effect":{"sheet":"enemies.glitch-boss","name":"frobbitLand"},"offset":{"x":0,"y":0,"z":0}},{"rumbleType":"RANDOM","name":"","duration":0.4,"power":"STRONG","speed":"FASTEST","fade":true,"type":"RUMBLE_SCREEN"},{"wait":false,"viaWalkConfig":false,"type":"SHOW_ANIMATION","anim":"stomped"},{"aggroTime":0.2,"time":0.25,"type":"WAIT"},{"type":"CLEAR_ANIMATION"},{"duration":0,"align":"BOTTOM","rotateFace":0,"flipLeftFace":false,"wait":false,"waitSkip":0,"actionDetached":false,"fixPos":false,"type":"SHOW_EFFECT","effect":{"sheet":"dust","name":"backMedium"}},{"jumpSpeed":260,"adjustAbove":16,"type":"JUMP_TO_TARGET"},{"align":"BOTTOM","radius":24,"yScale":0,"zHeight":64,"centralAngle":0,"duration":0,"expandRadius":0,"alwaysFull":false,"clockwise":false,"flipLeftFace":0,"rectangular":false,"repeat":false,"uniformHitDir":false,"fixPos":false,"checkCollision":false,"type":"CIRCLE_ATTACK","attack":{"type":"MASSIVE","element":"NEUTRAL","damageFactor":1,"fly":"MASSIVE+","reverse":false,"spFactor":0,"guardable":"","skillBonus":"","limiter":""},"offset":{"x":0,"y":0,"z":0}},{"align":"BOTTOM","radius":56,"yScale":0,"zHeight":64,"centralAngle":0,"duration":0,"expandRadius":0,"alwaysFull":false,"clockwise":false,"flipLeftFace":0,"rectangular":false,"repeat":false,"uniformHitDir":false,"fixPos":false,"checkCollision":false,"type":"CIRCLE_ATTACK","attack":{"type":"MASSIVE","element":"WAVE","damageFactor":1.2,"reverse":false,"spFactor":0,"status":5,"guardable":"","skillBonus":"","limiter":""},"offset":{"x":0,"y":0,"z":0}},{"conditions":[{"min":1,"negated":false,"type":"HP_BREAK"}],"withElse":false,"type":"COMBAT_IF","thenStep":[{"volume":0.5,"variance":0.1,"global":false,"loop":false,"speed":1.5,"type":"PLAY_SOUND","sound":"media\/sound\/boss\/turret\/big-shot.ogg"},{"volume":0.6,"variance":0.1,"global":false,"loop":false,"speed":2,"type":"PLAY_SOUND","sound":"media\/sound\/battle\/wave-hit.ogg"},{"changeType":"add","type":"SET_ATTRIB_NUMBER","attribName":"temp","value":{"varName":"entity.attrib.temp"}},{"align":"BOTTOM","centralAngle":0.9,"angleVary":0,"startDistCollide":"NONE","random":false,"clockwise":false,"flipLeftFace":0,"circularArea":false,"uniformDir":0,"delay":0,"repeat":false,"duration":0.06,"type":"SHOOT_PROXY_RANGE","proxy":"homingBall","offset":{"x":0,"y":0,"z":0},"count":{"varName":"entity.attrib.temp"}}]},{"volume":1,"global":false,"loop":false,"type":"PLAY_SOUND","sound":"media\/sound\/battle\/thud-5.ogg"},{"duration":0,"align":"BOTTOM","rotateFace":0,"flipLeftFace":false,"wait":false,"waitSkip":0,"actionDetached":false,"fixPos":false,"type":"SHOW_EFFECT","effect":{"sheet":"enemies.glitch-boss","name":"frobbitLand"},"offset":{"x":0,"y":0,"z":0}},{"rumbleType":"RANDOM","name":"","duration":0.4,"power":"STRONG","speed":"FASTEST","fade":true,"type":"RUMBLE_SCREEN"},{"group":"line","type":"CLEAR_EFFECTS"},{"wait":false,"viaWalkConfig":false,"type":"SHOW_ANIMATION","anim":"stomped"},{"conditions":[{"min":2,"negated":false,"type":"HP_BREAK"}],"withElse":false,"type":"COMBAT_IF","thenStep":[{"aggroTime":0.2,"time":0.25,"type":"WAIT"},{"type":"CLEAR_ANIMATION"},{"duration":0,"align":"BOTTOM","rotateFace":0,"flipLeftFace":false,"wait":false,"waitSkip":0,"actionDetached":false,"fixPos":false,"type":"SHOW_EFFECT","effect":{"sheet":"dust","name":"backMedium"}},{"jumpSpeed":270,"adjustAbove":16,"type":"JUMP_TO_TARGET"},{"align":"BOTTOM","radius":24,"yScale":0,"zHeight":64,"centralAngle":0,"duration":0,"expandRadius":0,"alwaysFull":false,"clockwise":false,"flipLeftFace":0,"rectangular":false,"repeat":false,"uniformHitDir":false,"fixPos":false,"checkCollision":false,"type":"CIRCLE_ATTACK","attack":{"type":"MASSIVE","element":"NEUTRAL","damageFactor":1,"fly":"MASSIVE+","reverse":false,"spFactor":0,"guardable":"","skillBonus":"","limiter":""},"offset":{"x":0,"y":0,"z":0}},{"align":"BOTTOM","radius":56,"yScale":0,"zHeight":64,"centralAngle":0,"duration":0,"expandRadius":0,"alwaysFull":false,"clockwise":false,"flipLeftFace":0,"rectangular":false,"repeat":false,"uniformHitDir":false,"fixPos":false,"checkCollision":false,"type":"CIRCLE_ATTACK","attack":{"type":"MASSIVE","element":"WAVE","damageFactor":1.2,"reverse":false,"spFactor":0,"status":5,"guardable":"","skillBonus":"","limiter":""},"offset":{"x":0,"y":0,"z":0}},{"volume":0.5,"variance":0.1,"global":false,"loop":false,"speed":1.5,"type":"PLAY_SOUND","sound":"media\/sound\/boss\/turret\/big-shot.ogg"},{"volume":0.6,"variance":0.1,"global":false,"loop":false,"speed":2,"type":"PLAY_SOUND","sound":"media\/sound\/battle\/wave-hit.ogg"},{"changeType":"add","type":"SET_ATTRIB_NUMBER","attribName":"temp","value":{"varName":"entity.attrib.temp"}},{"align":"BOTTOM","centralAngle":0.6,"angleVary":0,"startDistCollide":"NONE","random":false,"clockwise":false,"flipLeftFace":0,"circularArea":false,"uniformDir":0,"delay":0,"repeat":false,"duration":0.06,"type":"SHOOT_PROXY_RANGE","proxy":"homingBall","offset":{"x":0,"y":0,"z":0},"count":5},{"volume":1,"global":false,"loop":false,"type":"PLAY_SOUND","sound":"media\/sound\/battle\/thud-5.ogg"},{"duration":0,"align":"BOTTOM","rotateFace":0,"flipLeftFace":false,"wait":false,"waitSkip":0,"actionDetached":false,"fixPos":false,"type":"SHOW_EFFECT","effect":{"sheet":"enemies.glitch-boss","name":"frobbitLand"},"offset":{"x":0,"y":0,"z":0}},{"rumbleType":"RANDOM","name":"","duration":0.4,"power":"STRONG","speed":"FASTEST","fade":true,"type":"RUMBLE_SCREEN"},{"group":"line","type":"CLEAR_EFFECTS"},{"wait":false,"viaWalkConfig":false,"type":"SHOW_ANIMATION","anim":"stomped"}]},{"value":false,"type":"FACE_TO_TARGET"},{"time":0.7,"type":"WAIT"},{"value":true,"type":"FACE_TO_TARGET"},{"aggroTime":0.5,"time":0.8,"type":"WAIT"}],"RangedAttack":[{"value":0.7,"type":"SET_RELATIVE_SPEED"},{"value":"MASSIVE","type":"SET_HIT_STABLE"},{"active":"PRE_ATTACK","type":"CHANGE_ENEMY_ANNOTATION"},{"type":"DISABLE_REACTION","reaction":"BALL_DODGE"},{"value":0.2,"type":"SET_RELATIVE_SPEED"},{"maxTime":0.3,"forceTime":false,"distance":64,"planOnly":false,"targetType":"ENEMY","precise":false,"type":"NAVIGATE_TO_TARGET"},{"value":true,"immediately":true,"type":"FACE_TO_TARGET"},{"value":1.2,"forwardToProxies":false,"type":"SET_DAMAGE_CEILING"},{"conditions":[{"min":2,"negated":false,"type":"HP_BREAK"}],"withElse":false,"type":"COMBAT_IF","thenStep":[{"value":1.5,"forwardToProxies":false,"type":"SET_DAMAGE_CEILING"}]},{"type":"SELECT_RANDOM","options":[{"0":" ","count":1,"weight":1},{"0":" ","count":1,"weight":1}],"0_0":[{"type":"ENABLE_REACTION","reaction":"WEAK_SPOT_COLD"},{"duration":-1,"align":"FACE","rotateFace":0,"flipLeftFace":false,"wait":false,"waitSkip":0,"actionDetached":false,"group":"charge","fixPos":false,"type":"SHOW_EFFECT","effect":{"sheet":"enemies.heat-dng","name":"mothBigCharge"},"offset":{"x":0,"y":0,"z":0}},{"time":1.1,"stopBeforeEdge":false,"type":"MOVE_FORWARD"},{"group":"charge","type":"CLEAR_EFFECTS"},{"wait":false,"viaWalkConfig":false,"type":"SHOW_ANIMATION","anim":"brake"},{"duration":-1,"align":"FACE","rotateFace":0,"flipLeftFace":false,"wait":false,"waitSkip":0,"actionDetached":false,"group":"shot","fixPos":false,"type":"SHOW_EFFECT","effect":{"sheet":"enemies.heat-dng","name":"darthMothLaserSrc"},"offset":{"x":0,"y":0,"z":0}},{"time":0.1,"type":"WAIT"},{"active":"ATTACK","type":"CHANGE_ENEMY_ANNOTATION"},{"value":false,"immediately":true,"type":"FACE_TO_TARGET"},{"align":"BOTTOM","centralAngle":0.2,"angleVary":0,"startDistCollide":"NONE","random":false,"clockwise":false,"flipLeftFace":0,"circularArea":false,"uniformDir":0,"delay":0,"repeat":false,"duration":0,"type":"SHOOT_PROXY_RANGE","proxy":"laser","offset":{"x":0,"y":0,"z":0},"count":{"varName":"entity.hpBreak"}},{"type":"DISABLE_REACTION","reaction":"WEAK_SPOT_COLD"}],"1_0":[{"type":"ENABLE_REACTION","reaction":"WEAK_SPOT_HEAT"},{"duration":-1,"align":"FACE","rotateFace":0,"flipLeftFace":false,"wait":false,"waitSkip":0,"actionDetached":false,"group":"charge","fixPos":false,"type":"SHOW_EFFECT","effect":{"sheet":"specials.cold","name":"coldMegaCharge"},"offset":{"x":0,"y":0,"z":0}},{"time":0.7,"stopBeforeEdge":false,"type":"MOVE_FORWARD"},{"group":"charge","type":"CLEAR_EFFECTS"},{"wait":false,"viaWalkConfig":false,"type":"SHOW_ANIMATION","anim":"brake"},{"duration":0.1,"align":"FACE","rotateFace":0,"flipLeftFace":false,"wait":false,"waitSkip":0,"actionDetached":false,"group":"shot","fixPos":false,"type":"SHOW_EFFECT","effect":{"sheet":"specials.cold","name":"coldQuickShoot"},"offset":{"x":0,"y":0,"z":0}},{"time":0.1,"type":"WAIT"},{"active":"ATTACK","type":"CHANGE_ENEMY_ANNOTATION"},{"value":false,"immediately":true,"type":"FACE_TO_TARGET"},{"changeType":"set","type":"SET_ATTRIB_NUMBER","attribName":"temp","value":{"varName":"entity.hpBreak"}},{"changeType":"mul","type":"SET_ATTRIB_NUMBER","attribName":"temp","value":2},{"changeType":"add","type":"SET_ATTRIB_NUMBER","attribName":"temp","value":1},{"align":"BOTTOM","centralAngle":0.1,"angleVary":0,"startDistCollide":"NONE","random":false,"clockwise":false,"flipLeftFace":0,"circularArea":false,"uniformDir":0,"delay":0,"repeat":false,"duration":0,"type":"SHOOT_PROXY_RANGE","proxy":"iceProjectilesSmall","offset":{"x":0,"y":0,"z":0},"count":{"varName":"entity.attrib.temp"}},{"type":"DISABLE_REACTION","reaction":"WEAK_SPOT_HEAT"}]},{"active":"POST_ATTACK","passive":"VULNERABLE","type":"CHANGE_ENEMY_ANNOTATION"},{"group":"shot","type":"CLEAR_EFFECTS"},{"type":"SET_RELATIVE_SPEED","value":1.5},{"time":0.1,"stopBeforeEdge":false,"type":"MOVE_BACKWARD"},{"value":0.5,"type":"SET_FRICTION"},{"aggroTime":0.9,"time":1.2,"type":"WAIT"}],"weakStart":[{"group":"weak","type":"CLEAR_EFFECTS"},{"duration":-1,"align":"BOTTOM","rotateFace":0,"flipLeftFace":false,"wait":false,"waitSkip":0,"actionDetached":true,"group":"weak","fixPos":false,"type":"SHOW_EFFECT","effect":{"sheet":"enemy","name":"angry2"},"offset":{"x":0,"y":0,"z":0}}],"weakEnd":[{"type":"DISABLE_REACTION","reaction":"BALL_DODGE"},{"group":"weak","type":"CLEAR_EFFECTS"},{"jumpHeight":"XL","wait":false,"ignoreSounds":false,"type":"JUMP"},{"value":true,"type":"FACE_TO_TARGET"}],"BallDodge":[{"type":"DISABLE_REACTION","reaction":"BALL_DODGE"},{"type":"SET_RELATIVE_SPEED","value":1.5},{"value":0.3,"type":"SET_INVINCIBLE"},{"duration":-1,"align":"CENTER","rotateFace":8,"flipLeftFace":false,"wait":false,"waitSkip":0,"actionDetached":false,"fixPos":false,"type":"SHOW_EFFECT","effect":{"sheet":"specials.wave","name":"waveDashTrail"},"offset":{"x":0,"y":0,"z":0}},{"value":true,"immediately":true,"type":"FACE_TO_TARGET"},{"value":true,"type":"SET_FACE_FIX"},{"conditions":[{"min":1,"negated":false,"type":"HP_BREAK"}],"withElse":false,"type":"COMBAT_IF","thenStep":[{"volume":0.5,"variance":0.1,"global":false,"loop":false,"speed":1.5,"type":"PLAY_SOUND","sound":"media\/sound\/boss\/turret\/big-shot.ogg"},{"volume":0.6,"variance":0.1,"global":false,"loop":false,"speed":2,"type":"PLAY_SOUND","sound":"media\/sound\/battle\/wave-hit.ogg"},{"align":"BOTTOM","centralAngle":0,"angleVary":0.1,"startDistCollide":"NONE","random":false,"clockwise":false,"flipLeftFace":0,"circularArea":false,"uniformDir":0,"delay":0,"repeat":false,"duration":0.04,"type":"SHOOT_PROXY_RANGE","proxy":"homingBall","offset":{"x":0,"y":0,"z":0},"count":{"varName":"entity.hpBreak"}}]},{"maxTime":0.6,"distance":48,"planOnly":false,"dodgeType":"NEUTRAL","type":"NAVIGATE_DODGE"}],"hpBreak":[{"value":0.5,"type":"SET_DAMAGE_FACTOR"}],"removeAura":[{"value":"MASSIVE","type":"SET_HIT_STABLE"},{"sticking":true,"group":"pushAura","ignoreSelf":false,"type":"REMOVE_PROXIES"},{"name":"shield","type":"REMOVE_SHIELD"},{"type":"RESET_TRACKER","tracker":"auraRegen"},{"duration":0,"align":"BOTTOM","rotateFace":0,"flipLeftFace":false,"wait":false,"waitSkip":0,"actionDetached":true,"fixPos":false,"type":"SHOW_EFFECT","effect":{"sheet":"specials.wave","name":"waveGunBounce"},"offset":{"x":0,"y":0,"z":0}},{"text":{"en_US":"[ AURA DISPERSED ]","pt_BR":"[ AURA DISPERSADA ]","langUid":47,"de_DE":"[ AURA AUFGEL\u00d6ST ]","ja_JP":"[\u30aa\u30fc\u30e9\u5206\u6563]<<A<<[CHANGED 2021\/02\/09]","ko_KR":"[ \uc624\ub77c \ud769\uc5b4\uc9d0 ]<<A<<[CHANGED 2021\/02\/16]","zh_TW":"<<A<<[CHANGED 2021\/02\/19]","zh_CN":"[ \u5149\u73af\u89e3\u9664 ]<<A<<[CHANGED 2021\/02\/19]"},"mode":"NO_LINE","color":"GREEN","actionDetached":true,"hideOutsideOfScreen":false,"type":"SHOW_AR_MSG","time":3}],"restoreAura":[{"group":"weak","type":"CLEAR_EFFECTS"},{"type":"DISABLE_REACTION","reaction":"SHOCK_SHIELDBREAK"},{"type":"DISABLE_REACTION","reaction":"BALL_DODGE"},{"value":"MASSIVE","type":"SET_HIT_STABLE"},{"value":0.3,"type":"SET_DAMAGE_FACTOR"},{"value":true,"immediately":true,"type":"FACE_TO_TARGET"},{"type":"WAIT","time":0.1},{"duration":-1,"align":"BOTTOM","rotateFace":0,"flipLeftFace":false,"wait":false,"waitSkip":0,"actionDetached":false,"group":"charge","fixPos":false,"type":"SHOW_EFFECT","effect":{"sheet":"enemies.glitch-boss","name":"frobbitCharge"},"offset":{"x":0,"y":0,"z":0}},{"jumpHeight":"L","wait":true,"ignoreSounds":false,"type":"JUMP"},{"text":{"en_US":"[ RESTORED AURA ]","pt_BR":"[ AURA RESTAURADA ]","langUid":45,"de_DE":"[ AURA ERNEUERT ]","ja_JP":"[\u30aa\u30fc\u30e9\u56de\u5fa9]<<A<<[CHANGED 2021\/02\/09]","ko_KR":"[ \uc624\ub77c \ubcf5\uad6c ]<<A<<[CHANGED 2021\/02\/16]","zh_TW":"<<A<<[CHANGED 2021\/02\/19]","zh_CN":"[ \u5149\u73af\u6062\u590d ]<<A<<[CHANGED 2021\/02\/19]"},"mode":"NO_LINE","color":"RED","actionDetached":true,"hideOutsideOfScreen":false,"type":"SHOW_AR_MSG","time":2},{"group":"charge","type":"CLEAR_EFFECTS"},{"name":"shield","actionDetached":true,"type":"ADD_SHIELD","shield":{"type":"DIRECTIONAL","settings":{"baseFactor":0.5,"strength":"BLOCK_ALL","stableOverride":"MASSIVE","duration":-1,"range":1,"back":false}}},{"align":"BOTTOM","type":"SHOOT_PROXY","proxy":"wavePushAura","offset":{"x":0,"y":0,"z":0}},{"target":"PROXY_OWNER","align":"BOTTOM","duration":0,"type":"STICK_TO_TARGET","offset":{"x":0,"y":0,"z":0}},{"type":"HEAL_STATUS"},{"conditions":[{"negated":false,"type":"TRACKER_READY","name":"dash"}],"withElse":true,"type":"COMBAT_IF","thenStep":[{"forceValue":0.7,"type":"RESET_TRACKER","tracker":"dash"}],"elseStep":[{"type":"RESET_TRACKER","tracker":"dash"}]},{"aggroTime":0.3,"type":"WAIT","time":0.4}],"kill":[]},"reactions":{"DASH_WALL_HIT":{"action":"DashWallHit","angle":0.2,"type":"MOVEMENT_BLOCK"},"WEAK_SPOT":{"hitType":"REGULAR","preAction":"weakStart","preSwitchState":"WEAK","blockFurtherHits":false,"damageFactor":1.5,"attackType":"MASSIVE","flyLevel":"","stunChange":"FORCE_STUN","alignFace":false,"dramaticEffect":"BREAK","conditions":[{"type":"!BALL_SMALL"},{"name":"shield","type":"!HAS_SHIELD"}],"ignoreFailed":false,"type":"HIT_REACTION"},"WEAK_SPOT_HEAT":{"hitType":"REGULAR","preAction":"weakStart","preSwitchState":"WEAK","blockFurtherHits":false,"damageFactor":2,"attackType":"MASSIVE","flyLevel":"","stunChange":"FORCE_STUN","alignFace":false,"dramaticEffect":"BREAK","conditions":[{"type":"!BALL_SMALL"},{"element":"HEAT","negated":false,"type":"ELEMENT_HIT"},{"name":"shield","type":"!HAS_SHIELD"}],"ignoreFailed":false,"type":"HIT_REACTION"},"WEAK_SPOT_COLD":{"hitType":"REGULAR","preAction":"weakStart","preSwitchState":"WEAK","blockFurtherHits":false,"damageFactor":2,"attackType":"MASSIVE","flyLevel":"","stunChange":"FORCE_STUN","alignFace":false,"dramaticEffect":"BREAK","conditions":[{"type":"!BALL_SMALL"},{"element":"COLD","negated":false,"type":"ELEMENT_HIT"},{"name":"shield","type":"!HAS_SHIELD"}],"ignoreFailed":false,"type":"HIT_REACTION"},"BALL_DODGE":{"action":"BallDodge","viewAngle":0.2,"restartPrevAction":false,"probability":2,"count":1,"blockTime":1.4,"conditions":[{"negated":false,"type":"IS_BALL"}],"type":"DODGE"},"SHOCK_SHIELDBREAK":{"hitType":"REGULAR","preAction":"removeAura","blockFurtherHits":false,"attackType":"BREAK","flyLevel":"","stunChange":"FORCE_STABLE","alignFace":false,"dramaticEffect":"BREAK","conditions":[{"element":"SHOCK","negated":false,"type":"ELEMENT_HIT"},{"sticking":false,"group":"pushAura","negated":false,"type":"HAS_PROXY"},{"name":"shield","negated":false,"type":"HAS_SHIELD"},{"negated":false,"type":"TRACKER_READY","name":"shockHits"}],"ignoreFailed":false,"type":"HIT_REACTION"},"HP_BREAK":{"hitType":"HP_BREAK_HIT","preAction":"hpBreak","preSwitchState":"DEFAULT","action":"restoreAura","blockFurtherHits":false,"attackType":"BREAK","flyLevel":"MASSIVE+","stunChange":"FORCE_STUN","alignFace":false,"dramaticEffect":"HP_BREAK_ZOOM","conditions":[],"ignoreFailed":false,"type":"HIT_REACTION"},"KILL_HIT":{"hitType":"KILL_HIT","preAction":"kill","blockFurtherHits":false,"attackType":"MASSIVE","flyLevel":"MASSIVE","stunChange":"FORCE_STUN","alignFace":false,"dramaticEffect":"","conditions":[],"ignoreFailed":false,"type":"HIT_REACTION"}},"meta":{"species":{"en_US":"Shaking Robot","pt_BR":"Robô Balançante","de_DE":"Tremor-Roboter<<C<<Gepr\u00fcft: Minsu","zh_CN":"\u9707\u98a4\u673a\u5175<<A<<[CHANGED 2021\/02\/19]","zh_TW":"\u7926\u4e95\u6a5f\u5175<<A<<[CHANGED 2021\/02\/19]","ja_JP":"\u632f\u52d5\u30ed\u30dc\u30c3\u30c8<<A<<[CHANGED 2021\/02\/09]","ko_KR":"\ub5a0\ub294 \ub85c\ubd07<<A<<[CHANGED 2021\/02\/16]","langUid":36},"category":"MECHA","descriptions":[{"text":{"en_US":"A variant of the \\v[combat.name.mine-runbot] that seems to be constantly shaking when active. This is because of the powerful \\c[3]Tremor Core\\c[0] that was implemented.\nUnlike its much colder design brethren, this unique machine attacks with a broader variety of elements and prefers powerful \\c[3]Wave\\c[0] attacks.","de_DE":"Eine Variante des Carritrich, der permanent zittert, wenn er aktiv ist. Das liegt an dem leistungsstarken \\c[3]Tremorkern\\c[0], der implementiert wurde.\nIm Gegensatz zu seinen viel k\u00e4lteren Design-Br\u00fcdern greift diese einzigartige Maschine mit einer breiteren Palette von Elementen an und bevorzugt leistungsstarke \\c[3]Welle\\c[0]-Angriffe.<<C<<Gepr\u00fcft: Minsu","zh_CN":"\\v[combat.name.mine-runbot]\u7684\u4e9a\u79cd\uff0c\u6fc0\u6d3b\u540e\u4f3c\u4e4e\u5728\u4e0d\u65ad\u98a4\u52a8\u3002\u8fd9\u662f\u56e0\u4e3a\u5176\u4f53\u5185\u5b89\u88c5\u7684\u5f3a\u5927\u9707\u98a4\u6838\u5fc3\u3002\n\u548c\u5176\u51b0\u51bb\u539f\u4f53\u4e0d\u540c\uff0c\u8fd9\u4e2a\u72ec\u7279\u7684\u673a\u5175\u4f1a\u4f7f\u7528\u5404\u79cd\u5143\u7d20\u8fdb\u884c\u653b\u51fb\uff0c\u5e76\u4e14\u504f\u597d\u5f3a\u5927\u7684\\c[3]\u6ce2\u7eb9\\c[0]\u6253\u51fb\u3002<<A<<[CHANGED 2021\/03\/30]","zh_TW":"\u642c\u904b\u6771\u897f\u7684\u9d15\u9ce5\u3002\u4e0d\u904e\u5148\u7956\u4e4b\u8def\u6c7a\u5b9a\u5b83\u5011\u4e0d\u9700\u8981\u518d\u70ba\u4eba\u985e\u904b\u9001\u7926\u77f3\u4e86\uff0c\u800c\u662f\u70ba\u90a3\u4e9b\u81bd\u6562\u5165\u4fb5\u795e\u5edf\u7684\u4eba\u5e36\u53bb\u75db\u82e6\u3002\u5b83\u5011\u6703\u50cf\\c[3]\\v[area.autumn-area.name]\\c[0]\u7684\u725b\u985e\u4e00\u6a23\u767c\u8d77\u885d\u92d2\uff0c\u800c\u4e0d\u540c\u7684\u662f\uff0c\u4f60\u9700\u8981\u5728\u5b83\u5011\u649e\u5230\u7246\u4e0a\u4e4b\u524d\u5c0d\u5b83\u5011\u9032\u884c\u653b\u64ca\uff0c\u624d\u80fd\u64ca\u6688\u5b83\u5011\u3002<<A<<[CHANGED 2021\/03\/30]","ja_JP":"\\v[combat.name.autumn-fall\/runbot-tremor]\u306e\u5909\u7570\u578b\u3067\u3001\u30d1\u30ef\u30fc\u306e\u3042\u308b\\c[3]\u632f\u52d5\u30b3\u30a2\\c[0]\u304c\u5b9f\u88c5\u3055\u308c\u3066\u3044\u308b\u305f\u3081\u8d77\u52d5\u4e2d\u306f\u5e38\u306b\u632f\u52d5\u3057\u3066\u3044\u308b\u3002\n\u540c\u7a2e\u306e\u6c37\u5c5e\u6027\u306e\u30ed\u30dc\u30c3\u30c8\u3068\u3057\u3066\u306f\u73cd\u3057\u304f\u3001\u3053\u306e\u5909\u308f\u3063\u305f\u30de\u30b7\u30f3\u306f\u3055\u307e\u3056\u307e\u306a\u30a8\u30ec\u30e1\u30f3\u30c8\u3092\u99c6\u4f7f\u3057\u3001\u5f37\u3044\\c[3]\u6ce2\u52d5\\c[0]\u653b\u6483\u3092\u597d\u3080\u3002<<A<<[CHANGED 2021\/03\/30]","ko_KR":"\ucf1c\uc838 \uc788\uc744 \ub550 \ud56d\uc0c1 \ub35c\ub35c \ub5a0\ub294 \\v[combat.name.mine-runbot]\uc758 \ubcc0\ud615\uc785\ub2c8\ub2e4. \uadf8 \uc774\uc720\ub294 \ud0d1\uc7ac\ub41c \uac15\ub825\ud55c \\c[3]\uc9c4\ub3d9 \ud575\\c[0] \ub54c\ubb38\uc774\uc8e0.\n\uc774 \ub3c5\ud2b9\ud55c \uae30\uacc4\ub294 \ub354 \ucc28\uac00\uc6b4 \ub514\uc790\uc778\uc758 \uac19\uc740 \uc885\uacfc \ub2ec\ub9ac, \uc18d\uc131\uc744 \ub2e4\uc591\ud558\uac8c \uc0ac\uc6a9\ud558\uba70 \ud2b9\ud788 \uac15\ub825\ud55c \\c[3]\ud30c\ub3d9\\c[0] \uacf5\uaca9\uc744 \uc120\ud638\ud569\ub2c8\ub2e4.<<A<<[CHANGED 2021\/03\/30]","langUid":40},"condition":""}]}}