{
    "DOCTYPE": "AREAS_MAP",
    "name": {
        "en_US": "untitled",
        "pt_BR": "Sem título",
        "de_DE": "unbenannt",
        "langUid": 1,
        "zh_CN": "\u672a\u547d\u540d<<A<<[CHANGED 2018\/03\/14]",
        "ko_KR": "\ubbf8\uc815<<A<<[CHANGED 2018\/03\/14]",
        "ja_JP": "\u7121\u984c<<A<<[CHANGED 2018\/03\/14]",
        "zh_TW": "\u672a\u547d\u540d<<A<<[CHANGED 2018\/03\/14]"
    },
    "width": 50,
    "height": 50,
    "floors": [{
        "level": 0,
        "name": {
            "en_US": "G",
            "langUid": 2,
            "zh_CN": "G<<A<<[CHANGED 2018\/03\/14]",
            "ko_KR": "G<<A<<[CHANGED 2018\/03\/14]",
            "ja_JP": "\u5730\u968e<<A<<[CHANGED 2018\/03\/14]",
            "de_DE": "EG",
            "zh_TW": "G<<A<<[CHANGED 2018\/03\/14]"
        },
        "tiles": [
            [0, 0, 0, 0, 0, 0, 0, 0, 0, 0, 0, 0, 0, 0, 0, 0, 0, 0, 0, 0, 0, 0, 0, 0, 0, 0, 0, 0, 0, 0, 0, 0, 0, 0, 0, 0, 0, 0, 0, 0, 0, 0, 0, 0, 0, 0, 0, 0, 0, 0],
            [0, 0, 0, 0, 0, 0, 0, 0, 0, 0, 0, 0, 0, 0, 0, 0, 0, 0, 0, 0, 0, 0, 0, 0, 0, 0, 0, 0, 0, 0, 0, 0, 0, 0, 0, 7, 7, 7, 0, 0, 0, 0, 0, 0, 0, 0, 0, 0, 0, 0],
            [0, 0, 0, 0, 0, 0, 0, 0, 0, 0, 0, 0, 0, 0, 0, 0, 0, 0, 0, 0, 0, 0, 0, 0, 0, 0, 0, 0, 0, 0, 0, 0, 0, 0, 0, 7, 7, 7, 0, 0, 0, 0, 0, 0, 0, 0, 0, 0, 0, 0],
            [0, 0, 0, 0, 0, 0, 0, 0, 0, 0, 0, 0, 0, 0, 0, 0, 0, 0, 0, 0, 13, 13, 13, 13, 13, 0, 0, 0, 0, 0, 0, 0, 0, 0, 0, 0, 7, 0, 0, 0, 0, 0, 0, 0, 0, 0, 0, 0, 0, 0],
            [0, 0, 0, 0, 0, 0, 0, 0, 0, 0, 0, 0, 0, 0, 0, 0, 0, 0, 0, 0, 13, 13, 13, 13, 13, 0, 0, 0, 0, 0, 0, 0, 0, 0, 7, 7, 7, 7, 7, 0, 0, 0, 0, 0, 0, 0, 0, 0, 0, 0],
            [0, 0, 0, 0, 0, 0, 0, 0, 0, 0, 0, 0, 0, 0, 0, 0, 0, 0, 0, 0, 13, 13, 13, 13, 13, 0, 0, 0, 0, 0, 0, 0, 0, 0, 7, 7, 7, 7, 7, 0, 0, 0, 0, 0, 0, 0, 0, 0, 0, 0],
            [0, 0, 0, 0, 0, 0, 0, 0, 0, 0, 0, 0, 0, 0, 0, 0, 0, 0, 0, 0, 0, 0, 0, 0, 0, 0, 0, 0, 0, 0, 0, 0, 0, 0, 7, 7, 7, 7, 7, 0, 0, 0, 0, 0, 0, 0, 0, 0, 0, 0],
            [0, 0, 0, 0, 0, 0, 0, 0, 0, 0, 0, 0, 0, 0, 0, 0, 0, 0, 0, 0, 0, 0, 0, 0, 0, 0, 0, 0, 0, 0, 0, 0, 0, 0, 0, 0, 0, 0, 0, 0, 0, 0, 0, 0, 0, 0, 0, 0, 0, 0],
            [0, 0, 0, 0, 0, 0, 0, 0, 0, 0, 0, 0, 0, 0, 0, 0, 0, 0, 0, 0, 0, 0, 0, 0, 0, 0, 0, 0, 0, 0, 0, 0, 0, 0, 0, 0, 0, 0, 0, 0, 0, 0, 0, 0, 0, 0, 0, 0, 0, 0],
            [0, 0, 0, 0, 0, 0, 0, 0, 0, 0, 0, 0, 0, 0, 0, 0, 0, 0, 0, 0, 0, 0, 0, 0, 0, 0, 0, 0, 0, 0, 0, 0, 0, 0, 0, 0, 0, 0, 0, 0, 0, 0, 0, 0, 0, 0, 0, 0, 0, 0],
            [0, 0, 0, 0, 0, 0, 0, 0, 0, 4, 4, 4, 4, 4, 0, 0, 0, 0, 0, 0, 0, 0, 0, 0, 0, 0, 0, 0, 0, 0, 0, 0, 0, 0, 0, 0, 0, 0, 0, 0, 0, 0, 0, 0, 0, 0, 0, 0, 0, 0],
            [0, 0, 0, 0, 0, 0, 0, 0, 0, 4, 4, 4, 4, 4, 0, 0, 0, 0, 0, 0, 0, 0, 0, 0, 0, 0, 0, 0, 0, 0, 0, 0, 0, 0, 0, 0, 0, 0, 0, 0, 0, 0, 0, 0, 0, 0, 0, 0, 0, 0],
            [0, 0, 0, 0, 0, 0, 0, 0, 0, 4, 4, 4, 4, 4, 0, 0, 0, 0, 0, 0, 0, 0, 0, 0, 0, 0, 0, 0, 0, 0, 0, 0, 0, 0, 0, 10, 10, 10, 10, 10, 10, 10, 10, 10, 10, 0, 0, 0, 0, 0],
            [0, 0, 0, 0, 0, 0, 0, 0, 0, 0, 0, 0, 0, 0, 0, 0, 0, 0, 0, 0, 0, 0, 0, 0, 0, 0, 0, 0, 0, 0, 0, 0, 0, 0, 0, 10, 10, 10, 10, 10, 10, 10, 10, 10, 10, 0, 0, 0, 0, 0],
            [0, 0, 0, 0, 0, 0, 0, 0, 0, 0, 0, 0, 0, 0, 0, 0, 0, 0, 0, 0, 0, 0, 0, 0, 0, 0, 5, 5, 5, 0, 0, 0, 0, 0, 0, 10, 10, 10, 10, 10, 10, 10, 10, 10, 10, 0, 0, 0, 0, 0],
            [0, 0, 0, 0, 0, 0, 0, 0, 0, 0, 0, 0, 0, 0, 0, 0, 0, 0, 0, 0, 0, 0, 0, 0, 0, 0, 5, 5, 5, 0, 0, 0, 0, 0, 0, 10, 10, 10, 10, 10, 10, 10, 10, 10, 10, 0, 0, 0, 0, 0],
            [0, 0, 0, 0, 0, 0, 0, 0, 0, 0, 12, 12, 12, 12, 12, 0, 0, 0, 0, 0, 0, 0, 0, 0, 0, 0, 5, 5, 5, 0, 0, 0, 0, 0, 0, 10, 10, 10, 10, 10, 10, 10, 10, 10, 10, 0, 0, 0, 0, 0],
            [0, 0, 0, 0, 0, 0, 0, 0, 0, 12, 12, 12, 12, 12, 12, 12, 0, 0, 0, 0, 0, 0, 0, 0, 0, 0, 5, 5, 5, 0, 0, 0, 0, 0, 0, 0, 0, 0, 0, 0, 0, 0, 0, 0, 0, 0, 0, 0, 0, 0],
            [0, 0, 0, 0, 0, 0, 0, 0, 0, 12, 12, 12, 12, 12, 12, 12, 0, 0, 0, 0, 0, 0, 0, 0, 0, 0, 5, 5, 5, 0, 0, 0, 0, 0, 0, 0, 0, 0, 0, 0, 0, 0, 0, 0, 0, 0, 0, 0, 0, 0],
            [0, 0, 0, 0, 0, 0, 0, 0, 0, 12, 12, 12, 12, 12, 12, 12, 0, 0, 0, 0, 0, 0, 0, 0, 0, 0, 0, 0, 0, 0, 0, 0, 0, 0, 0, 0, 0, 0, 0, 0, 0, 0, 0, 0, 0, 0, 0, 0, 0, 0],
            [0, 0, 0, 0, 0, 0, 0, 0, 0, 0, 12, 12, 12, 12, 12, 0, 0, 0, 0, 0, 0, 0, 0, 0, 0, 0, 0, 0, 0, 0, 0, 0, 0, 0, 6, 6, 6, 6, 6, 0, 0, 0, 0, 0, 0, 0, 0, 0, 0, 0],
            [0, 0, 0, 0, 0, 0, 0, 0, 0, 0, 0, 0, 0, 0, 0, 0, 0, 0, 0, 0, 0, 0, 0, 0, 0, 0, 0, 0, 0, 0, 0, 0, 0, 0, 6, 6, 6, 6, 6, 0, 0, 0, 0, 0, 0, 0, 0, 0, 0, 0],
            [0, 0, 0, 0, 0, 0, 0, 0, 0, 0, 0, 0, 0, 0, 0, 0, 0, 0, 0, 0, 0, 0, 0, 0, 0, 0, 0, 0, 0, 0, 0, 0, 0, 0, 6, 6, 6, 6, 6, 0, 0, 0, 0, 0, 0, 0, 0, 0, 0, 0],
            [0, 0, 0, 0, 0, 0, 0, 0, 0, 0, 0, 0, 0, 0, 0, 0, 0, 0, 0, 0, 0, 0, 0, 0, 0, 0, 0, 0, 0, 0, 0, 0, 0, 0, 0, 0, 0, 0, 0, 0, 0, 0, 0, 0, 0, 0, 0, 0, 0, 0],
            [0, 0, 0, 0, 0, 0, 0, 0, 0, 0, 0, 0, 0, 0, 0, 0, 0, 0, 0, 0, 0, 0, 0, 0, 0, 0, 0, 0, 0, 0, 0, 0, 0, 0, 0, 0, 0, 0, 0, 0, 0, 0, 0, 0, 0, 0, 0, 0, 0, 0],
            [0, 0, 0, 0, 0, 0, 0, 0, 0, 0, 0, 0, 0, 0, 0, 3, 3, 3, 3, 3, 2, 2, 2, 2, 2, 2, 2, 2, 2, 0, 0, 0, 0, 0, 0, 0, 0, 0, 0, 0, 0, 0, 0, 0, 0, 0, 0, 0, 0, 0],
            [0, 0, 0, 0, 0, 0, 0, 0, 0, 0, 0, 0, 0, 0, 0, 3, 3, 3, 3, 3, 2, 2, 2, 2, 2, 2, 2, 2, 2, 0, 0, 0, 0, 0, 0, 0, 0, 0, 0, 0, 0, 0, 0, 0, 0, 0, 0, 0, 0, 0],
            [0, 0, 0, 0, 0, 0, 0, 0, 0, 0, 0, 0, 0, 0, 0, 3, 3, 3, 3, 3, 2, 2, 2, 2, 2, 2, 2, 2, 2, 0, 0, 0, 0, 0, 0, 0, 0, 11, 11, 11, 11, 11, 11, 0, 0, 0, 0, 0, 0, 0],
            [0, 0, 0, 0, 0, 0, 0, 0, 0, 0, 0, 0, 0, 0, 0, 0, 0, 0, 0, 0, 0, 0, 1, 1, 1, 1, 1, 0, 0, 0, 0, 0, 0, 0, 0, 0, 0, 11, 11, 11, 11, 11, 11, 0, 0, 0, 0, 0, 0, 0],
            [0, 0, 0, 0, 0, 0, 0, 0, 0, 0, 0, 0, 0, 0, 0, 0, 0, 0, 0, 0, 0, 0, 1, 1, 1, 1, 1, 0, 0, 0, 0, 0, 0, 0, 0, 0, 0, 11, 11, 11, 11, 11, 11, 0, 0, 0, 0, 0, 0, 0],
            [0, 0, 0, 0, 0, 0, 0, 0, 0, 0, 0, 0, 0, 0, 0, 0, 0, 0, 0, 0, 0, 0, 1, 1, 1, 1, 1, 0, 0, 0, 0, 0, 0, 0, 0, 0, 0, 11, 11, 11, 11, 11, 11, 0, 0, 0, 0, 0, 0, 0],
            [0, 0, 0, 0, 0, 0, 0, 0, 0, 0, 0, 0, 0, 0, 0, 0, 0, 0, 0, 0, 0, 0, 1, 1, 1, 1, 1, 0, 0, 0, 0, 0, 0, 0, 0, 0, 0, 0, 0, 0, 0, 0, 0, 0, 0, 0, 0, 0, 0, 0],
            [0, 0, 0, 0, 0, 0, 0, 0, 0, 0, 0, 0, 0, 0, 0, 0, 0, 0, 0, 0, 0, 0, 0, 0, 0, 0, 0, 0, 0, 0, 0, 0, 0, 0, 0, 0, 0, 0, 0, 0, 0, 0, 0, 0, 0, 0, 0, 0, 0, 0],
            [0, 0, 0, 0, 0, 0, 0, 0, 0, 0, 0, 0, 0, 0, 0, 0, 0, 0, 0, 0, 0, 0, 0, 0, 0, 0, 0, 0, 0, 0, 0, 0, 0, 0, 0, 0, 0, 0, 0, 0, 0, 0, 0, 0, 0, 0, 0, 0, 0, 0],
            [0, 0, 0, 0, 0, 0, 0, 0, 0, 0, 0, 0, 0, 0, 0, 0, 0, 0, 0, 0, 0, 0, 0, 0, 0, 0, 0, 0, 0, 0, 0, 0, 0, 0, 0, 0, 0, 0, 0, 0, 0, 0, 0, 0, 0, 0, 0, 0, 0, 0],
            [0, 0, 0, 0, 0, 0, 0, 0, 0, 0, 0, 0, 0, 0, 0, 0, 0, 0, 0, 0, 0, 0, 0, 0, 0, 0, 0, 0, 0, 0, 0, 0, 0, 0, 0, 0, 0, 0, 0, 0, 0, 0, 0, 0, 0, 0, 0, 0, 0, 0],
            [0, 0, 0, 0, 0, 0, 0, 0, 0, 0, 0, 0, 0, 0, 0, 0, 0, 0, 0, 0, 0, 0, 0, 0, 0, 0, 0, 0, 0, 0, 0, 0, 0, 0, 0, 0, 0, 0, 0, 0, 0, 0, 0, 0, 0, 0, 0, 0, 0, 0],
            [0, 0, 0, 0, 0, 0, 0, 0, 0, 0, 0, 0, 0, 0, 0, 0, 0, 0, 0, 0, 0, 0, 0, 0, 0, 0, 0, 0, 0, 0, 0, 0, 0, 0, 0, 0, 0, 0, 0, 0, 0, 0, 0, 0, 0, 0, 0, 0, 0, 0],
            [0, 0, 0, 0, 0, 0, 0, 0, 0, 0, 0, 0, 0, 0, 0, 0, 0, 0, 0, 0, 0, 0, 0, 0, 0, 0, 0, 0, 0, 0, 0, 0, 0, 0, 0, 0, 0, 0, 0, 0, 0, 0, 0, 0, 0, 0, 0, 0, 0, 0],
            [0, 0, 0, 0, 0, 0, 0, 0, 0, 0, 0, 0, 0, 0, 0, 0, 0, 0, 0, 0, 0, 0, 0, 0, 0, 0, 0, 0, 0, 0, 0, 0, 0, 0, 0, 0, 0, 0, 0, 0, 0, 0, 0, 0, 0, 0, 0, 0, 0, 0],
            [0, 0, 0, 0, 0, 0, 0, 0, 0, 0, 0, 0, 0, 0, 0, 0, 0, 0, 0, 0, 0, 0, 0, 0, 0, 0, 0, 0, 0, 0, 0, 0, 0, 0, 0, 0, 0, 0, 0, 0, 0, 0, 0, 0, 0, 0, 0, 0, 0, 0],
            [0, 0, 0, 0, 0, 0, 0, 0, 0, 0, 0, 0, 0, 0, 0, 0, 0, 0, 0, 0, 0, 0, 0, 0, 0, 0, 0, 0, 0, 0, 0, 0, 0, 0, 0, 0, 0, 0, 0, 0, 0, 0, 0, 0, 0, 0, 0, 0, 0, 0],
            [0, 0, 0, 0, 0, 0, 0, 0, 0, 0, 0, 0, 0, 0, 0, 0, 0, 0, 0, 0, 0, 0, 0, 0, 0, 0, 0, 0, 0, 0, 0, 0, 0, 0, 0, 0, 0, 0, 0, 0, 0, 0, 0, 0, 0, 0, 0, 0, 0, 0],
            [0, 0, 0, 0, 0, 0, 0, 0, 0, 0, 0, 0, 0, 0, 0, 0, 0, 0, 0, 0, 0, 0, 0, 0, 0, 0, 0, 0, 0, 0, 0, 0, 0, 0, 0, 0, 0, 0, 0, 0, 0, 0, 0, 0, 0, 0, 0, 0, 0, 0],
            [0, 0, 0, 0, 0, 0, 0, 0, 0, 0, 0, 0, 0, 0, 0, 0, 0, 0, 0, 0, 0, 0, 0, 0, 0, 0, 0, 0, 0, 0, 0, 0, 0, 0, 0, 0, 0, 0, 0, 0, 0, 0, 0, 0, 0, 0, 0, 0, 0, 0],
            [0, 0, 0, 0, 0, 0, 0, 0, 0, 0, 0, 0, 0, 0, 0, 0, 0, 0, 0, 0, 0, 0, 0, 0, 0, 0, 0, 0, 0, 0, 0, 0, 0, 0, 0, 0, 0, 0, 0, 0, 0, 0, 0, 0, 0, 0, 0, 0, 0, 0],
            [0, 0, 0, 0, 0, 0, 0, 0, 0, 0, 0, 0, 0, 0, 0, 0, 0, 0, 0, 0, 0, 0, 0, 0, 0, 0, 0, 0, 0, 0, 0, 0, 0, 0, 0, 0, 0, 0, 0, 0, 0, 0, 0, 0, 0, 0, 0, 0, 0, 0],
            [0, 0, 0, 0, 0, 0, 0, 0, 0, 0, 0, 0, 0, 0, 0, 0, 0, 0, 0, 0, 0, 0, 0, 0, 0, 0, 0, 0, 0, 0, 0, 0, 0, 0, 0, 0, 0, 0, 0, 0, 0, 0, 0, 0, 0, 0, 0, 0, 0, 0],
            [0, 0, 0, 0, 0, 0, 0, 0, 0, 0, 0, 0, 0, 0, 0, 0, 0, 0, 0, 0, 0, 0, 0, 0, 0, 0, 0, 0, 0, 0, 0, 0, 0, 0, 0, 0, 0, 0, 0, 0, 0, 0, 0, 0, 0, 0, 0, 0, 0, 0],
            [0, 0, 0, 0, 0, 0, 0, 0, 0, 0, 0, 0, 0, 0, 0, 0, 0, 0, 0, 0, 0, 0, 0, 0, 0, 0, 0, 0, 0, 0, 0, 0, 0, 0, 0, 0, 0, 0, 0, 0, 0, 0, 0, 0, 0, 0, 0, 0, 0, 0]
        ],
        "icons": [{
            "icon": "area_down",
            "x": 196,
            "y": 260,
            "map": 0,
            "data": {
                "area": "arid",
                "map": "arid.tower-1"
            }
        }],
        "maps": [{
            "path": "arid-dng.first.room-01",
            "offset": {
                "x": 0,
                "y": 0
            },
            "dungeon": "",
            "name": {
                "en_US": "Entry Test",
                "pt_BR": "Entrada de Testes",
                "langUid": 35,
                "de_DE": "Eingangspr\u00fcfung",
                "ja_JP": "\u6700\u521d\u306e\u8a66\u9a13<<A<<[CHANGED 2018\/08\/01]",
                "ko_KR": "\uc785\uc7a5 \uc2dc\ud5d8<<A<<[CHANGED 2018\/08\/01]",
                "zh_CN": "\u51c6\u5165\u6d4b\u8bd5<<A<<[CHANGED 2018\/08\/01]",
                "zh_TW": "\u6e96\u5165\u6e2c\u8a66<<A<<[CHANGED 2018\/08\/01]"
            }
        }, {
            "path": "arid-dng.first.room-02",
            "offset": {
                "x": 0,
                "y": 0
            },
            "dungeon": "",
            "name": {
                "en_US": "Pit of Time",
                "pt_BR": "Poço do tempo",
                "langUid": 36,
                "de_DE": "Grube der Zeit",
                "ja_JP": "\u6642\u306e\u7a74\u9053<<A<<[CHANGED 2018\/08\/01]",
                "ko_KR": "\uc2dc\uac04\uc758 \uad6c\uba4d<<A<<[CHANGED 2018\/08\/01]",
                "zh_CN": "\u65f6\u5149\u7ade\u6280\u573a<<A<<[CHANGED 2018\/08\/01]",
                "zh_TW": "\u6642\u5149\u7adf\u6280\u5834<<A<<[CHANGED 2018\/08\/01]"
            }
        }, {
            "path": "arid-dng.first.room-03",
            "offset": {
                "x": 0,
                "y": 0
            },
            "dungeon": "",
            "name": {
                "en_US": "Infected Room",
                "pt_BR": "Sala Infestada",
                "langUid": 37,
                "de_DE": "Infizierter Raum",
                "ja_JP": "\u611f\u67d3\u3057\u305f\u90e8\u5c4b<<A<<[CHANGED 2018\/08\/01]",
                "ko_KR": "\uac10\uc5fc\ub41c \ubc29<<A<<[CHANGED 2018\/08\/01]",
                "zh_CN": "\u88ab\u611f\u67d3\u7684\u623f\u95f4<<A<<[CHANGED 2018\/08\/01]",
                "zh_TW": "\u88ab\u611f\u67d3\u7684\u623f\u9593<<A<<[CHANGED 2018\/08\/01]"
            }
        }, {
            "path": "arid-dng.first.room-04",
            "offset": {
                "x": 0,
                "y": 0
            },
            "dungeon": "",
            "name": {
                "en_US": "Bombs and Ice",
                "pt_BR": "Bombas de gelo",
                "langUid": 39,
                "de_DE": "Bomben und Eis",
                "ja_JP": "\u7206\u5f3e\u3068\u6c37\u3068<<A<<[CHANGED 2018\/08\/01]",
                "ko_KR": "\ud3ed\ud0c4\uacfc \uc5bc\uc74c<<A<<[CHANGED 2018\/08\/01]",
                "zh_CN": "\u70b8\u5f39\u4e0e\u51b0<<A<<[CHANGED 2018\/08\/01]",
                "zh_TW": "\u70b8\u5f48\u8207\u51b0<<A<<[CHANGED 2018\/08\/01]"
            }
        }, {
            "path": "arid-dng.first.room-05",
            "offset": {
                "x": 0,
                "y": 0
            },
            "dungeon": "",
            "name": {
                "en_US": "Shocking Revelation",
                "pt_BR": "Revelação Chocante",
                "langUid": 41,
                "de_DE": "Schockierende Enth\u00fcllung",
                "ja_JP": "\u885d\u6483\u306e\u66b4\u9732<<A<<[CHANGED 2018\/08\/01]",
                "ko_KR": "\uc9dc\ub9bf\ud55c \ud3ed\ub85c<<A<<[CHANGED 2018\/08\/01]",
                "zh_CN": "\u60ca\u559c<<A<<[CHANGED 2018\/08\/01]",
                "zh_TW": "\u9a5a\u559c<<A<<[CHANGED 2018\/08\/01]"
            }
        }, {
            "path": "arid-dng.first.room-06",
            "offset": {
                "x": 0,
                "y": 0
            },
            "dungeon": "",
            "name": {
                "en_US": "Winter Infection",
                "pt_BR": "Infestação Invernal",
                "langUid": 42,
                "de_DE": "Winterinfektion",
                "ja_JP": "\u4f1d\u67d3\u3059\u308b\u51ac<<A<<[CHANGED 2018\/08\/01]",
                "ko_KR": "\uaca8\uc6b8 \uac10\uc5fc<<A<<[CHANGED 2018\/08\/01]",
                "zh_CN": "\u51ac\u4e4b\u611f\u67d3<<A<<[CHANGED 2018\/08\/01]",
                "zh_TW": "\u51ac\u4e4b\u611f\u67d3<<A<<[CHANGED 2018\/08\/01]"
            }
        }, {
            "path": "arid-dng.first.room-07",
            "offset": {
                "x": 0,
                "y": 0
            },
            "dungeon": "",
            "name": {
                "en_US": "ERROR 404",
                "pt_BR": "ERRO 404",
                "langUid": 44,
                "de_DE": "Fehler 404",
                "ja_JP": "404\u30a8\u30e9\u30fc<<A<<[CHANGED 2018\/08\/01]",
                "ko_KR": "\uc624\ub958 404<<A<<[CHANGED 2018\/08\/01]",
                "zh_CN": "ERROR 404<<A<<[CHANGED 2018\/08\/01]",
                "zh_TW": "ERROR 404<<A<<[CHANGED 2018\/08\/01]"
            }
        }, {
            "path": "arid-dng.first.jump-last",
            "offset": {
                "x": 0,
                "y": 0
            },
            "dungeon": "NO_DUNGEON",
            "name": {
                "en_US": "???",
                "pt_BR": "???",
                "langUid": 6,
                "zh_CN": "???<<A<<[CHANGED 2018\/08\/01]",
                "ko_KR": "????<<A<<[CHANGED 2018\/08\/01]",
                "ja_JP": "????<<A<<[CHANGED 2018\/08\/01]",
                "de_DE": "???",
                "zh_TW": "???<<A<<[CHANGED 2018\/08\/01]"
            }
        }, {
            "path": "arid-dng.first.outside",
            "name": {
                "en_US": "???",
                "pt_BR": "???",
                "langUid": 5,
                "zh_CN": "???<<A<<[CHANGED 2018\/08\/01]",
                "ko_KR": "????<<A<<[CHANGED 2018\/08\/01]",
                "ja_JP": "????<<A<<[CHANGED 2018\/08\/01]",
                "de_DE": "???",
                "zh_TW": "???<<A<<[CHANGED 2018\/08\/01]"
            },
            "offset": {
                "x": 0,
                "y": 0
            },
            "dungeon": "NO_DUNGEON"
        }, {
            "path": "arid-dng.first.room-08",
            "offset": {
                "x": 0,
                "y": 0
            },
            "dungeon": "",
            "name": {
                "en_US": "Chasing Rabbits",
                "pt_BR": "Coelhos Perseguidores",
                "langUid": 46,
                "de_DE": "Hasen jagen",
                "ja_JP": "\u30a6\u30b5\u30ae\u306e\u8ffd\u8de1<<A<<[CHANGED 2018\/08\/01]",
                "ko_KR": "\ud1a0\ub07c \ucd94\uc801<<A<<[CHANGED 2018\/08\/01]",
                "zh_CN": "\u7fa4\u96c4\u9010\u5154<<A<<[CHANGED 2018\/08\/01]",
                "zh_TW": "\u7fa4\u96c4\u9010\u5154<<A<<[CHANGED 2018\/08\/01]"
            }
        }, {
            "path": "arid-dng.first.room-09",
            "offset": {
                "x": 0,
                "y": 0
            },
            "dungeon": "",
            "name": {
                "en_US": "Bomb Switch",
                "pt_BR": "Interruptor de Bomba",
                "langUid": 47,
                "de_DE": "Bombenschalter",
                "ja_JP": "\u7206\u5f3e\u306e\u30b9\u30a4\u30c3\u30c1<<A<<[CHANGED 2018\/08\/01]",
                "ko_KR": "\ud3ed\ud0c4 \uc2a4\uc704\uce58<<A<<[CHANGED 2018\/08\/01]",
                "zh_CN": "\u70b8\u5f39\u5f00\u5173<<A<<[CHANGED 2018\/08\/01]",
                "zh_TW": "\u70b8\u5f48\u958b\u95dc<<A<<[CHANGED 2018\/08\/01]"
            }
        }, {
            "path": "arid-dng.first.room-10",
            "offset": {
                "x": 0,
                "y": 0
            },
            "dungeon": "",
            "name": {
                "en_US": "Testing Grounds",
                "pt_BR": "Campo de Testes",
                "langUid": 48,
                "de_DE": "Testgrund",
                "ja_JP": "\u30c6\u30b9\u30c8\u5834<<A<<[CHANGED 2018\/08\/01]",
                "ko_KR": "\uc2dc\ud5d8\uc7a5<<A<<[CHANGED 2018\/08\/01]",
                "zh_CN": "\u6d4b\u8bd5\u623f<<A<<[CHANGED 2018\/08\/01]",
                "zh_TW": "\u6e2c\u8a66\u623f<<A<<[CHANGED 2018\/08\/01]"
            }
        }, {
            "path": "arid-dng.first.room-11",
            "name": {
                "en_US": "INVALID INSTANCE",
                "pt_BR": "INSTANCIA INVALIDA",
                "langUid": 24,
                "zh_CN": "INVALID INSTANCE<<A<<[CHANGED 2018\/08\/01]",
                "ko_KR": "\ube44\uc720\ud6a8 \uac1c\ubcc4 \ubc29<<A<<[CHANGED 2018\/08\/01]",
                "ja_JP": "\u4e0d\u6b63\u306a\u30a4\u30f3\u30b9\u30bf\u30f3\u30b9<<A<<[CHANGED 2018\/08\/01]",
                "de_DE": "UNG\u00dcLTIGE INSTANZ",
                "zh_TW": "INVALID INSTANCE<<A<<[CHANGED 2018\/08\/01]"
            },
            "offset": {
                "x": 0,
                "y": 0
            },
            "dungeon": "NO_DUNGEON"
        }],
        "connections": [{
            "tx": 24,
            "ty": 27,
            "dir": "VERTICAL",
            "size": 1,
            "map1": 1,
            "map2": 0
        }, {
            "tx": 19,
            "ty": 26,
            "dir": "HORIZONTAL",
            "size": 1,
            "map1": 2,
            "map2": 1
        }],
        "landmarks": []
    }],
    "chests": 0,
    "defaultFloor": 0
}